00_source/button.v
module button(Fg_CLK,RESETn,ExtBTN,IntBTN);
    input Fg_CLK;
    input RESETn;
    input  ExtBTN;
    output reg IntBTN;

    reg D1;
    reg D2;
    reg D3;
    reg [25:0] counter;
    reg enable_counter;

    `ifdef TEST_MODE parameter [25:0] time_counter_limit = 300 ; //for test
    `else            parameter [25:0] time_counter_limit = 7200000;// 100ms;
    `endif
    // parameter [25:0] time_counter_limit =  2_400_000 ; //for 100 ms
    // parameter [25:0] time_counter_limit = 24_000_000 ; //for 1 sec
    
always @(posedge Fg_CLK or negedge RESETn) begin
    if(~RESETn)begin
            D1 <= 0;
            D2 <= 0;
            D3 <= 0;
    end
    else begin
        D1 <= ExtBTN;
        D2 <= D1;
        D3 <= D2;
        if(~enable_counter) IntBTN <= (~D2 & D3 &(counter == 0));
    end
end


always @(posedge Fg_CLK or negedge RESETn) begin
    if(~RESETn)begin
        counter <= 0;
    end
    else if(counter < time_counter_limit && (enable_counter == 1))begin
        counter <= counter + 1;
    end
    else begin //in case coumter >= time_counter_limit
        counter <= 0;
        enable_counter <= 0;
    end
end

always @(posedge Fg_CLK or negedge RESETn) begin
    if(~RESETn)begin
        enable_counter <= 0 ;
    end

    else if(IntBTN)begin
        enable_counter <= 1;
    end

end

endmodule

01_vsim/01_testbench/button_tb.sv
`timescale 1ps/1ps

module button_tb();

    // ----------- registers -----------
    reg Fg_CLK_i=1;
    reg task_CLK=1;
    reg RESETn_i=0;
    reg ExtBTN_i=1;

    // ----------- wires -----------
    wire IntBTN_o;

    //---------------task-------------
    task press();
        begin

            for (integer i=0; i<10; i++ ) begin
                ExtBTN_i<=~ExtBTN_i;
                @(posedge task_CLK);
                
            end

            for (integer i=0; i<20; i++ ) begin
                ExtBTN_i<=0;
                @(posedge task_CLK);
            end

            for (integer i=0; i<10; i++ ) begin
                ExtBTN_i<=~ExtBTN_i;
                @(posedge task_CLK);
                
            end

            ExtBTN_i <=1;


        end
    endtask

    // ----------- device under test -----------
    button button_module(
        .Fg_CLK(Fg_CLK_i),
        .RESETn(RESETn_i),
        .ExtBTN(ExtBTN_i),
        .IntBTN(IntBTN_o)
    );

    // ----------- system signal generator-----------
    always #(41_666/2) Fg_CLK_i = ~Fg_CLK_i; //24M
    always #(50_000/2) task_CLK = ~task_CLK; // clk for task press
    // ----------- test scenarios -----------
    initial begin
        repeat(10)@(posedge Fg_CLK_i);
        #10_000 RESETn_i = 1;
        $display("Starting test");
        repeat(100)@(posedge Fg_CLK_i);
        #10 press();
        repeat(400)@(posedge Fg_CLK_i);
        press();
        repeat(1000)@(posedge Fg_CLK_i);
        $stop;
    end

    // ----------- dumping wave -----------
    initial begin
        $dumpfile("button_tb.vcd");
        $dumpvars(0,button_tb);
        
    end
    
endmodule

01_vsim/button_tb.vcd
$date
	Sat Jul  6 09:24:20 2024
$end
$version
	ModelSim Version 2020.1
$end
$timescale
	1ps
$end

$scope module button_tb $end
$var reg 1 ! Fg_CLK_i $end
$var reg 1 " task_CLK $end
$var reg 1 # RESETn_i $end
$var reg 1 $ ExtBTN_i $end
$var wire 1 % IntBTN_o $end

$scope task press $end
$upscope $end

$scope module button_module $end
$var parameter 26 & time_counter_limit $end
$var wire 1 ' Fg_CLK $end
$var wire 1 ( RESETn $end
$var wire 1 ) ExtBTN $end
$var reg 1 * IntBTN $end
$var reg 1 + D1 $end
$var reg 1 , D2 $end
$var reg 1 - D3 $end
$var reg 26 . counter [25:0] $end
$var reg 1 / enable_counter $end
$upscope $end
$upscope $end
$enddefinitions $end
#0
$dumpvars
1!
1"
0#
1$
x*
0+
0,
0-
b0 .
0/
b100101100 &
x%
1'
0(
1)
$end
#20833
0!
0'
#25000
0"
#41666
1!
1'
#50000
1"
#62499
0!
0'
#75000
0"
#83332
1!
1'
#100000
1"
#104165
0!
0'
#124998
1!
1'
#125000
0"
#145831
0!
0'
#150000
1"
#166664
1!
1'
#175000
0"
#187497
0!
0'
#200000
1"
#208330
1!
1'
#225000
0"
#229163
0!
0'
#249996
1!
1'
#250000
1"
#270829
0!
0'
#275000
0"
#291662
1!
1'
#300000
1"
#312495
0!
0'
#325000
0"
#333328
1!
1'
#350000
1"
#354161
0!
0'
#374994
1!
1'
#375000
0"
#395827
0!
0'
#400000
1"
#416660
1!
1'
#425000
0"
#426660
1#
1(
#437493
0!
0'
#450000
1"
#458326
1!
1'
1+
0*
0%
#475000
0"
#479159
0!
0'
#499992
1!
1'
1,
#500000
1"
#520825
0!
0'
#525000
0"
#541658
1!
1'
1-
#550000
1"
#562491
0!
0'
#575000
0"
#583324
1!
1'
#600000
1"
#604157
0!
0'
#624990
1!
1'
#625000
0"
#645823
0!
0'
#650000
1"
#666656
1!
1'
#675000
0"
#687489
0!
0'
#700000
1"
#708322
1!
1'
#725000
0"
#729155
0!
0'
#749988
1!
1'
#750000
1"
#770821
0!
0'
#775000
0"
#791654
1!
1'
#800000
1"
#812487
0!
0'
#825000
0"
#833320
1!
1'
#850000
1"
#854153
0!
0'
#874986
1!
1'
#875000
0"
#895819
0!
0'
#900000
1"
#916652
1!
1'
#925000
0"
#937485
0!
0'
#950000
1"
#958318
1!
1'
#975000
0"
#979151
0!
0'
#999984
1!
1'
#1000000
1"
#1020817
0!
0'
#1025000
0"
#1041650
1!
1'
#1050000
1"
#1062483
0!
0'
#1075000
0"
#1083316
1!
1'
#1100000
1"
#1104149
0!
0'
#1124982
1!
1'
#1125000
0"
#1145815
0!
0'
#1150000
1"
#1166648
1!
1'
#1175000
0"
#1187481
0!
0'
#1200000
1"
#1208314
1!
1'
#1225000
0"
#1229147
0!
0'
#1249980
1!
1'
#1250000
1"
#1270813
0!
0'
#1275000
0"
#1291646
1!
1'
#1300000
1"
#1312479
0!
0'
#1325000
0"
#1333312
1!
1'
#1350000
1"
#1354145
0!
0'
#1374978
1!
1'
#1375000
0"
#1395811
0!
0'
#1400000
1"
#1416644
1!
1'
#1425000
0"
#1437477
0!
0'
#1450000
1"
#1458310
1!
1'
#1475000
0"
#1479143
0!
0'
#1499976
1!
1'
#1500000
1"
#1520809
0!
0'
#1525000
0"
#1541642
1!
1'
#1550000
1"
#1562475
0!
0'
#1575000
0"
#1583308
1!
1'
#1600000
1"
#1604141
0!
0'
#1624974
1!
1'
#1625000
0"
#1645807
0!
0'
#1650000
1"
#1666640
1!
1'
#1675000
0"
#1687473
0!
0'
#1700000
1"
#1708306
1!
1'
#1725000
0"
#1729139
0!
0'
#1749972
1!
1'
#1750000
1"
#1770805
0!
0'
#1775000
0"
#1791638
1!
1'
#1800000
1"
#1812471
0!
0'
#1825000
0"
#1833304
1!
1'
#1850000
1"
#1854137
0!
0'
#1874970
1!
1'
#1875000
0"
#1895803
0!
0'
#1900000
1"
#1916636
1!
1'
#1925000
0"
#1937469
0!
0'
#1950000
1"
#1958302
1!
1'
#1975000
0"
#1979135
0!
0'
#1999968
1!
1'
#2000000
1"
#2020801
0!
0'
#2025000
0"
#2041634
1!
1'
#2050000
1"
#2062467
0!
0'
#2075000
0"
#2083300
1!
1'
#2100000
1"
#2104133
0!
0'
#2124966
1!
1'
#2125000
0"
#2145799
0!
0'
#2150000
1"
#2166632
1!
1'
#2175000
0"
#2187465
0!
0'
#2200000
1"
#2208298
1!
1'
#2225000
0"
#2229131
0!
0'
#2249964
1!
1'
#2250000
1"
#2270797
0!
0'
#2275000
0"
#2291630
1!
1'
#2300000
1"
#2312463
0!
0'
#2325000
0"
#2333296
1!
1'
#2350000
1"
#2354129
0!
0'
#2374962
1!
1'
#2375000
0"
#2395795
0!
0'
#2400000
1"
#2416628
1!
1'
#2425000
0"
#2437461
0!
0'
#2450000
1"
#2458294
1!
1'
#2475000
0"
#2479127
0!
0'
#2499960
1!
1'
#2500000
1"
#2520793
0!
0'
#2525000
0"
#2541626
1!
1'
#2550000
1"
#2562459
0!
0'
#2575000
0"
#2583292
1!
1'
#2600000
1"
#2604125
0!
0'
#2624958
1!
1'
#2625000
0"
#2645791
0!
0'
#2650000
1"
#2666624
1!
1'
#2675000
0"
#2687457
0!
0'
#2700000
1"
#2708290
1!
1'
#2725000
0"
#2729123
0!
0'
#2749956
1!
1'
#2750000
1"
#2770789
0!
0'
#2775000
0"
#2791622
1!
1'
#2800000
1"
#2812455
0!
0'
#2825000
0"
#2833288
1!
1'
#2850000
1"
#2854121
0!
0'
#2874954
1!
1'
#2875000
0"
#2895787
0!
0'
#2900000
1"
#2916620
1!
1'
#2925000
0"
#2937453
0!
0'
#2950000
1"
#2958286
1!
1'
#2975000
0"
#2979119
0!
0'
#2999952
1!
1'
#3000000
1"
#3020785
0!
0'
#3025000
0"
#3041618
1!
1'
#3050000
1"
#3062451
0!
0'
#3075000
0"
#3083284
1!
1'
#3100000
1"
#3104117
0!
0'
#3124950
1!
1'
#3125000
0"
#3145783
0!
0'
#3150000
1"
#3166616
1!
1'
#3175000
0"
#3187449
0!
0'
#3200000
1"
#3208282
1!
1'
#3225000
0"
#3229115
0!
0'
#3249948
1!
1'
#3250000
1"
#3270781
0!
0'
#3275000
0"
#3291614
1!
1'
#3300000
1"
#3312447
0!
0'
#3325000
0"
#3333280
1!
1'
#3350000
1"
#3354113
0!
0'
#3374946
1!
1'
#3375000
0"
#3395779
0!
0'
#3400000
1"
#3416612
1!
1'
#3425000
0"
#3437445
0!
0'
#3450000
1"
#3458278
1!
1'
#3475000
0"
#3479111
0!
0'
#3499944
1!
1'
#3500000
1"
#3520777
0!
0'
#3525000
0"
#3541610
1!
1'
#3550000
1"
#3562443
0!
0'
#3575000
0"
#3583276
1!
1'
#3600000
1"
#3604109
0!
0'
#3624942
1!
1'
#3625000
0"
#3645775
0!
0'
#3650000
1"
#3666608
1!
1'
#3675000
0"
#3687441
0!
0'
#3700000
1"
#3708274
1!
1'
#3725000
0"
#3729107
0!
0'
#3749940
1!
1'
#3750000
1"
#3770773
0!
0'
#3775000
0"
#3791606
1!
1'
#3800000
1"
#3812439
0!
0'
#3825000
0"
#3833272
1!
1'
#3850000
1"
#3854105
0!
0'
#3874938
1!
1'
#3875000
0"
#3895771
0!
0'
#3900000
1"
#3916604
1!
1'
#3925000
0"
#3937437
0!
0'
#3950000
1"
#3958270
1!
1'
#3975000
0"
#3979103
0!
0'
#3999936
1!
1'
#4000000
1"
#4020769
0!
0'
#4025000
0"
#4041602
1!
1'
#4050000
1"
#4062435
0!
0'
#4075000
0"
#4083268
1!
1'
#4100000
1"
#4104101
0!
0'
#4124934
1!
1'
#4125000
0"
#4145767
0!
0'
#4150000
1"
#4166600
1!
1'
#4175000
0"
#4187433
0!
0'
#4200000
1"
#4208266
1!
1'
#4225000
0"
#4229099
0!
0'
#4249932
1!
1'
#4250000
1"
#4270765
0!
0'
#4275000
0"
#4291598
1!
1'
#4300000
1"
#4312431
0!
0'
#4325000
0"
#4333264
1!
1'
#4350000
1"
#4354097
0!
0'
#4374930
1!
1'
#4375000
0"
#4395763
0!
0'
#4400000
1"
#4416596
1!
1'
#4425000
0"
#4437429
0!
0'
#4450000
1"
#4458262
1!
1'
#4475000
0"
#4479095
0!
0'
#4499928
1!
1'
#4500000
1"
#4520761
0!
0'
#4525000
0"
#4541594
1!
1'
#4550000
1"
#4562427
0!
0'
#4575000
0"
#4583260
1!
1'
#4583270
0$
0)
#4600000
1"
1$
1)
#4604093
0!
0'
#4624926
1!
1'
#4625000
0"
#4645759
0!
0'
#4650000
1"
0$
0)
#4666592
1!
1'
0+
#4675000
0"
#4687425
0!
0'
#4700000
1"
1$
1)
#4708258
1!
1'
1+
0,
#4725000
0"
#4729091
0!
0'
#4749924
1!
1'
1,
0-
1*
1%
#4750000
1"
0$
0)
#4770757
0!
0'
#4775000
0"
#4791590
1!
1'
0+
1-
0*
1/
0%
#4800000
1"
1$
1)
#4812423
0!
0'
#4825000
0"
#4833256
1!
1'
1+
0,
b1 .
#4850000
1"
0$
0)
#4854089
0!
0'
#4874922
1!
1'
0+
1,
0-
b10 .
#4875000
0"
#4895755
0!
0'
#4900000
1"
1$
1)
#4916588
1!
1'
1+
0,
1-
b11 .
#4925000
0"
#4937421
0!
0'
#4950000
1"
0$
0)
#4958254
1!
1'
0+
1,
0-
b100 .
#4975000
0"
#4979087
0!
0'
#4999920
1!
1'
0,
1-
b101 .
#5000000
1"
1$
1)
#5020753
0!
0'
#5025000
0"
#5041586
1!
1'
1+
0-
b110 .
#5050000
1"
0$
0)
#5062419
0!
0'
#5075000
0"
#5083252
1!
1'
0+
1,
b111 .
#5100000
1"
#5104085
0!
0'
#5124918
1!
1'
0,
1-
b1000 .
#5125000
0"
#5145751
0!
0'
#5150000
1"
#5166584
1!
1'
0-
b1001 .
#5175000
0"
#5187417
0!
0'
#5200000
1"
#5208250
1!
1'
b1010 .
#5225000
0"
#5229083
0!
0'
#5249916
1!
1'
b1011 .
#5250000
1"
#5270749
0!
0'
#5275000
0"
#5291582
1!
1'
b1100 .
#5300000
1"
#5312415
0!
0'
#5325000
0"
#5333248
1!
1'
b1101 .
#5350000
1"
#5354081
0!
0'
#5374914
1!
1'
b1110 .
#5375000
0"
#5395747
0!
0'
#5400000
1"
#5416580
1!
1'
b1111 .
#5425000
0"
#5437413
0!
0'
#5450000
1"
#5458246
1!
1'
b10000 .
#5475000
0"
#5479079
0!
0'
#5499912
1!
1'
b10001 .
#5500000
1"
#5520745
0!
0'
#5525000
0"
#5541578
1!
1'
b10010 .
#5550000
1"
#5562411
0!
0'
#5575000
0"
#5583244
1!
1'
b10011 .
#5600000
1"
#5604077
0!
0'
#5624910
1!
1'
b10100 .
#5625000
0"
#5645743
0!
0'
#5650000
1"
#5666576
1!
1'
b10101 .
#5675000
0"
#5687409
0!
0'
#5700000
1"
#5708242
1!
1'
b10110 .
#5725000
0"
#5729075
0!
0'
#5749908
1!
1'
b10111 .
#5750000
1"
#5770741
0!
0'
#5775000
0"
#5791574
1!
1'
b11000 .
#5800000
1"
#5812407
0!
0'
#5825000
0"
#5833240
1!
1'
b11001 .
#5850000
1"
#5854073
0!
0'
#5874906
1!
1'
b11010 .
#5875000
0"
#5895739
0!
0'
#5900000
1"
#5916572
1!
1'
b11011 .
#5925000
0"
#5937405
0!
0'
#5950000
1"
#5958238
1!
1'
b11100 .
#5975000
0"
#5979071
0!
0'
#5999904
1!
1'
b11101 .
#6000000
1"
#6020737
0!
0'
#6025000
0"
#6041570
1!
1'
b11110 .
#6050000
1"
1$
1)
#6062403
0!
0'
#6075000
0"
#6083236
1!
1'
1+
b11111 .
#6100000
1"
0$
0)
#6104069
0!
0'
#6124902
1!
1'
0+
1,
b100000 .
#6125000
0"
#6145735
0!
0'
#6150000
1"
1$
1)
#6166568
1!
1'
1+
0,
1-
b100001 .
#6175000
0"
#6187401
0!
0'
#6200000
1"
0$
0)
#6208234
1!
1'
0+
1,
0-
b100010 .
#6225000
0"
#6229067
0!
0'
#6249900
1!
1'
0,
1-
b100011 .
#6250000
1"
1$
1)
#6270733
0!
0'
#6275000
0"
#6291566
1!
1'
1+
0-
b100100 .
#6300000
1"
0$
0)
#6312399
0!
0'
#6325000
0"
#6333232
1!
1'
0+
1,
b100101 .
#6350000
1"
1$
1)
#6354065
0!
0'
#6374898
1!
1'
1+
0,
1-
b100110 .
#6375000
0"
#6395731
0!
0'
#6400000
1"
0$
0)
#6416564
1!
1'
0+
1,
0-
b100111 .
#6425000
0"
#6437397
0!
0'
#6450000
1"
1$
1)
#6458230
1!
1'
1+
0,
1-
b101000 .
#6475000
0"
#6479063
0!
0'
#6499896
1!
1'
1,
0-
b101001 .
#6500000
1"
0$
0)
#6520729
0!
0'
#6525000
0"
#6541562
1!
1'
0+
1-
b101010 .
#6550000
1"
1$
1)
#6562395
0!
0'
#6575000
0"
#6583228
1!
1'
1+
0,
b101011 .
#6600000
1"
#6604061
0!
0'
#6624894
1!
1'
1,
0-
b101100 .
#6625000
0"
#6645727
0!
0'
#6650000
1"
#6666560
1!
1'
1-
b101101 .
#6675000
0"
#6687393
0!
0'
#6700000
1"
#6708226
1!
1'
b101110 .
#6725000
0"
#6729059
0!
0'
#6749892
1!
1'
b101111 .
#6750000
1"
#6770725
0!
0'
#6775000
0"
#6791558
1!
1'
b110000 .
#6800000
1"
#6812391
0!
0'
#6825000
0"
#6833224
1!
1'
b110001 .
#6850000
1"
#6854057
0!
0'
#6874890
1!
1'
b110010 .
#6875000
0"
#6895723
0!
0'
#6900000
1"
#6916556
1!
1'
b110011 .
#6925000
0"
#6937389
0!
0'
#6950000
1"
#6958222
1!
1'
b110100 .
#6975000
0"
#6979055
0!
0'
#6999888
1!
1'
b110101 .
#7000000
1"
#7020721
0!
0'
#7025000
0"
#7041554
1!
1'
b110110 .
#7050000
1"
#7062387
0!
0'
#7075000
0"
#7083220
1!
1'
b110111 .
#7100000
1"
#7104053
0!
0'
#7124886
1!
1'
b111000 .
#7125000
0"
#7145719
0!
0'
#7150000
1"
#7166552
1!
1'
b111001 .
#7175000
0"
#7187385
0!
0'
#7200000
1"
#7208218
1!
1'
b111010 .
#7225000
0"
#7229051
0!
0'
#7249884
1!
1'
b111011 .
#7250000
1"
#7270717
0!
0'
#7275000
0"
#7291550
1!
1'
b111100 .
#7300000
1"
#7312383
0!
0'
#7325000
0"
#7333216
1!
1'
b111101 .
#7350000
1"
#7354049
0!
0'
#7374882
1!
1'
b111110 .
#7375000
0"
#7395715
0!
0'
#7400000
1"
#7416548
1!
1'
b111111 .
#7425000
0"
#7437381
0!
0'
#7450000
1"
#7458214
1!
1'
b1000000 .
#7475000
0"
#7479047
0!
0'
#7499880
1!
1'
b1000001 .
#7500000
1"
#7520713
0!
0'
#7525000
0"
#7541546
1!
1'
b1000010 .
#7550000
1"
#7562379
0!
0'
#7575000
0"
#7583212
1!
1'
b1000011 .
#7600000
1"
#7604045
0!
0'
#7624878
1!
1'
b1000100 .
#7625000
0"
#7645711
0!
0'
#7650000
1"
#7666544
1!
1'
b1000101 .
#7675000
0"
#7687377
0!
0'
#7700000
1"
#7708210
1!
1'
b1000110 .
#7725000
0"
#7729043
0!
0'
#7749876
1!
1'
b1000111 .
#7750000
1"
#7770709
0!
0'
#7775000
0"
#7791542
1!
1'
b1001000 .
#7800000
1"
#7812375
0!
0'
#7825000
0"
#7833208
1!
1'
b1001001 .
#7850000
1"
#7854041
0!
0'
#7874874
1!
1'
b1001010 .
#7875000
0"
#7895707
0!
0'
#7900000
1"
#7916540
1!
1'
b1001011 .
#7925000
0"
#7937373
0!
0'
#7950000
1"
#7958206
1!
1'
b1001100 .
#7975000
0"
#7979039
0!
0'
#7999872
1!
1'
b1001101 .
#8000000
1"
#8020705
0!
0'
#8025000
0"
#8041538
1!
1'
b1001110 .
#8050000
1"
#8062371
0!
0'
#8075000
0"
#8083204
1!
1'
b1001111 .
#8100000
1"
#8104037
0!
0'
#8124870
1!
1'
b1010000 .
#8125000
0"
#8145703
0!
0'
#8150000
1"
#8166536
1!
1'
b1010001 .
#8175000
0"
#8187369
0!
0'
#8200000
1"
#8208202
1!
1'
b1010010 .
#8225000
0"
#8229035
0!
0'
#8249868
1!
1'
b1010011 .
#8250000
1"
#8270701
0!
0'
#8275000
0"
#8291534
1!
1'
b1010100 .
#8300000
1"
#8312367
0!
0'
#8325000
0"
#8333200
1!
1'
b1010101 .
#8350000
1"
#8354033
0!
0'
#8374866
1!
1'
b1010110 .
#8375000
0"
#8395699
0!
0'
#8400000
1"
#8416532
1!
1'
b1010111 .
#8425000
0"
#8437365
0!
0'
#8450000
1"
#8458198
1!
1'
b1011000 .
#8475000
0"
#8479031
0!
0'
#8499864
1!
1'
b1011001 .
#8500000
1"
#8520697
0!
0'
#8525000
0"
#8541530
1!
1'
b1011010 .
#8550000
1"
#8562363
0!
0'
#8575000
0"
#8583196
1!
1'
b1011011 .
#8600000
1"
#8604029
0!
0'
#8624862
1!
1'
b1011100 .
#8625000
0"
#8645695
0!
0'
#8650000
1"
#8666528
1!
1'
b1011101 .
#8675000
0"
#8687361
0!
0'
#8700000
1"
#8708194
1!
1'
b1011110 .
#8725000
0"
#8729027
0!
0'
#8749860
1!
1'
b1011111 .
#8750000
1"
#8770693
0!
0'
#8775000
0"
#8791526
1!
1'
b1100000 .
#8800000
1"
#8812359
0!
0'
#8825000
0"
#8833192
1!
1'
b1100001 .
#8850000
1"
#8854025
0!
0'
#8874858
1!
1'
b1100010 .
#8875000
0"
#8895691
0!
0'
#8900000
1"
#8916524
1!
1'
b1100011 .
#8925000
0"
#8937357
0!
0'
#8950000
1"
#8958190
1!
1'
b1100100 .
#8975000
0"
#8979023
0!
0'
#8999856
1!
1'
b1100101 .
#9000000
1"
#9020689
0!
0'
#9025000
0"
#9041522
1!
1'
b1100110 .
#9050000
1"
#9062355
0!
0'
#9075000
0"
#9083188
1!
1'
b1100111 .
#9100000
1"
#9104021
0!
0'
#9124854
1!
1'
b1101000 .
#9125000
0"
#9145687
0!
0'
#9150000
1"
#9166520
1!
1'
b1101001 .
#9175000
0"
#9187353
0!
0'
#9200000
1"
#9208186
1!
1'
b1101010 .
#9225000
0"
#9229019
0!
0'
#9249852
1!
1'
b1101011 .
#9250000
1"
#9270685
0!
0'
#9275000
0"
#9291518
1!
1'
b1101100 .
#9300000
1"
#9312351
0!
0'
#9325000
0"
#9333184
1!
1'
b1101101 .
#9350000
1"
#9354017
0!
0'
#9374850
1!
1'
b1101110 .
#9375000
0"
#9395683
0!
0'
#9400000
1"
#9416516
1!
1'
b1101111 .
#9425000
0"
#9437349
0!
0'
#9450000
1"
#9458182
1!
1'
b1110000 .
#9475000
0"
#9479015
0!
0'
#9499848
1!
1'
b1110001 .
#9500000
1"
#9520681
0!
0'
#9525000
0"
#9541514
1!
1'
b1110010 .
#9550000
1"
#9562347
0!
0'
#9575000
0"
#9583180
1!
1'
b1110011 .
#9600000
1"
#9604013
0!
0'
#9624846
1!
1'
b1110100 .
#9625000
0"
#9645679
0!
0'
#9650000
1"
#9666512
1!
1'
b1110101 .
#9675000
0"
#9687345
0!
0'
#9700000
1"
#9708178
1!
1'
b1110110 .
#9725000
0"
#9729011
0!
0'
#9749844
1!
1'
b1110111 .
#9750000
1"
#9770677
0!
0'
#9775000
0"
#9791510
1!
1'
b1111000 .
#9800000
1"
#9812343
0!
0'
#9825000
0"
#9833176
1!
1'
b1111001 .
#9850000
1"
#9854009
0!
0'
#9874842
1!
1'
b1111010 .
#9875000
0"
#9895675
0!
0'
#9900000
1"
#9916508
1!
1'
b1111011 .
#9925000
0"
#9937341
0!
0'
#9950000
1"
#9958174
1!
1'
b1111100 .
#9975000
0"
#9979007
0!
0'
#9999840
1!
1'
b1111101 .
#10000000
1"
#10020673
0!
0'
#10025000
0"
#10041506
1!
1'
b1111110 .
#10050000
1"
#10062339
0!
0'
#10075000
0"
#10083172
1!
1'
b1111111 .
#10100000
1"
#10104005
0!
0'
#10124838
1!
1'
b10000000 .
#10125000
0"
#10145671
0!
0'
#10150000
1"
#10166504
1!
1'
b10000001 .
#10175000
0"
#10187337
0!
0'
#10200000
1"
#10208170
1!
1'
b10000010 .
#10225000
0"
#10229003
0!
0'
#10249836
1!
1'
b10000011 .
#10250000
1"
#10270669
0!
0'
#10275000
0"
#10291502
1!
1'
b10000100 .
#10300000
1"
#10312335
0!
0'
#10325000
0"
#10333168
1!
1'
b10000101 .
#10350000
1"
#10354001
0!
0'
#10374834
1!
1'
b10000110 .
#10375000
0"
#10395667
0!
0'
#10400000
1"
#10416500
1!
1'
b10000111 .
#10425000
0"
#10437333
0!
0'
#10450000
1"
#10458166
1!
1'
b10001000 .
#10475000
0"
#10478999
0!
0'
#10499832
1!
1'
b10001001 .
#10500000
1"
#10520665
0!
0'
#10525000
0"
#10541498
1!
1'
b10001010 .
#10550000
1"
#10562331
0!
0'
#10575000
0"
#10583164
1!
1'
b10001011 .
#10600000
1"
#10603997
0!
0'
#10624830
1!
1'
b10001100 .
#10625000
0"
#10645663
0!
0'
#10650000
1"
#10666496
1!
1'
b10001101 .
#10675000
0"
#10687329
0!
0'
#10700000
1"
#10708162
1!
1'
b10001110 .
#10725000
0"
#10728995
0!
0'
#10749828
1!
1'
b10001111 .
#10750000
1"
#10770661
0!
0'
#10775000
0"
#10791494
1!
1'
b10010000 .
#10800000
1"
#10812327
0!
0'
#10825000
0"
#10833160
1!
1'
b10010001 .
#10850000
1"
#10853993
0!
0'
#10874826
1!
1'
b10010010 .
#10875000
0"
#10895659
0!
0'
#10900000
1"
#10916492
1!
1'
b10010011 .
#10925000
0"
#10937325
0!
0'
#10950000
1"
#10958158
1!
1'
b10010100 .
#10975000
0"
#10978991
0!
0'
#10999824
1!
1'
b10010101 .
#11000000
1"
#11020657
0!
0'
#11025000
0"
#11041490
1!
1'
b10010110 .
#11050000
1"
#11062323
0!
0'
#11075000
0"
#11083156
1!
1'
b10010111 .
#11100000
1"
#11103989
0!
0'
#11124822
1!
1'
b10011000 .
#11125000
0"
#11145655
0!
0'
#11150000
1"
#11166488
1!
1'
b10011001 .
#11175000
0"
#11187321
0!
0'
#11200000
1"
#11208154
1!
1'
b10011010 .
#11225000
0"
#11228987
0!
0'
#11249820
1!
1'
b10011011 .
#11250000
1"
#11270653
0!
0'
#11275000
0"
#11291486
1!
1'
b10011100 .
#11300000
1"
#11312319
0!
0'
#11325000
0"
#11333152
1!
1'
b10011101 .
#11350000
1"
#11353985
0!
0'
#11374818
1!
1'
b10011110 .
#11375000
0"
#11395651
0!
0'
#11400000
1"
#11416484
1!
1'
b10011111 .
#11425000
0"
#11437317
0!
0'
#11450000
1"
#11458150
1!
1'
b10100000 .
#11475000
0"
#11478983
0!
0'
#11499816
1!
1'
b10100001 .
#11500000
1"
#11520649
0!
0'
#11525000
0"
#11541482
1!
1'
b10100010 .
#11550000
1"
#11562315
0!
0'
#11575000
0"
#11583148
1!
1'
b10100011 .
#11600000
1"
#11603981
0!
0'
#11624814
1!
1'
b10100100 .
#11625000
0"
#11645647
0!
0'
#11650000
1"
#11666480
1!
1'
b10100101 .
#11675000
0"
#11687313
0!
0'
#11700000
1"
#11708146
1!
1'
b10100110 .
#11725000
0"
#11728979
0!
0'
#11749812
1!
1'
b10100111 .
#11750000
1"
#11770645
0!
0'
#11775000
0"
#11791478
1!
1'
b10101000 .
#11800000
1"
#11812311
0!
0'
#11825000
0"
#11833144
1!
1'
b10101001 .
#11850000
1"
#11853977
0!
0'
#11874810
1!
1'
b10101010 .
#11875000
0"
#11895643
0!
0'
#11900000
1"
#11916476
1!
1'
b10101011 .
#11925000
0"
#11937309
0!
0'
#11950000
1"
#11958142
1!
1'
b10101100 .
#11975000
0"
#11978975
0!
0'
#11999808
1!
1'
b10101101 .
#12000000
1"
#12020641
0!
0'
#12025000
0"
#12041474
1!
1'
b10101110 .
#12050000
1"
#12062307
0!
0'
#12075000
0"
#12083140
1!
1'
b10101111 .
#12100000
1"
#12103973
0!
0'
#12124806
1!
1'
b10110000 .
#12125000
0"
#12145639
0!
0'
#12150000
1"
#12166472
1!
1'
b10110001 .
#12175000
0"
#12187305
0!
0'
#12200000
1"
#12208138
1!
1'
b10110010 .
#12225000
0"
#12228971
0!
0'
#12249804
1!
1'
b10110011 .
#12250000
1"
#12270637
0!
0'
#12275000
0"
#12291470
1!
1'
b10110100 .
#12300000
1"
#12312303
0!
0'
#12325000
0"
#12333136
1!
1'
b10110101 .
#12350000
1"
#12353969
0!
0'
#12374802
1!
1'
b10110110 .
#12375000
0"
#12395635
0!
0'
#12400000
1"
#12416468
1!
1'
b10110111 .
#12425000
0"
#12437301
0!
0'
#12450000
1"
#12458134
1!
1'
b10111000 .
#12475000
0"
#12478967
0!
0'
#12499800
1!
1'
b10111001 .
#12500000
1"
#12520633
0!
0'
#12525000
0"
#12541466
1!
1'
b10111010 .
#12550000
1"
#12562299
0!
0'
#12575000
0"
#12583132
1!
1'
b10111011 .
#12600000
1"
#12603965
0!
0'
#12624798
1!
1'
b10111100 .
#12625000
0"
#12645631
0!
0'
#12650000
1"
#12666464
1!
1'
b10111101 .
#12675000
0"
#12687297
0!
0'
#12700000
1"
#12708130
1!
1'
b10111110 .
#12725000
0"
#12728963
0!
0'
#12749796
1!
1'
b10111111 .
#12750000
1"
#12770629
0!
0'
#12775000
0"
#12791462
1!
1'
b11000000 .
#12800000
1"
#12812295
0!
0'
#12825000
0"
#12833128
1!
1'
b11000001 .
#12850000
1"
#12853961
0!
0'
#12874794
1!
1'
b11000010 .
#12875000
0"
#12895627
0!
0'
#12900000
1"
#12916460
1!
1'
b11000011 .
#12925000
0"
#12937293
0!
0'
#12950000
1"
#12958126
1!
1'
b11000100 .
#12975000
0"
#12978959
0!
0'
#12999792
1!
1'
b11000101 .
#13000000
1"
#13020625
0!
0'
#13025000
0"
#13041458
1!
1'
b11000110 .
#13050000
1"
#13062291
0!
0'
#13075000
0"
#13083124
1!
1'
b11000111 .
#13100000
1"
#13103957
0!
0'
#13124790
1!
1'
b11001000 .
#13125000
0"
#13145623
0!
0'
#13150000
1"
#13166456
1!
1'
b11001001 .
#13175000
0"
#13187289
0!
0'
#13200000
1"
#13208122
1!
1'
b11001010 .
#13225000
0"
#13228955
0!
0'
#13249788
1!
1'
b11001011 .
#13250000
1"
#13270621
0!
0'
#13275000
0"
#13291454
1!
1'
b11001100 .
#13300000
1"
#13312287
0!
0'
#13325000
0"
#13333120
1!
1'
b11001101 .
#13350000
1"
#13353953
0!
0'
#13374786
1!
1'
b11001110 .
#13375000
0"
#13395619
0!
0'
#13400000
1"
#13416452
1!
1'
b11001111 .
#13425000
0"
#13437285
0!
0'
#13450000
1"
#13458118
1!
1'
b11010000 .
#13475000
0"
#13478951
0!
0'
#13499784
1!
1'
b11010001 .
#13500000
1"
#13520617
0!
0'
#13525000
0"
#13541450
1!
1'
b11010010 .
