00_source/rotary.v
module rotary(Fg_CLK, RESETn, Rot_A, Rot_B, Rot_C, Address, FreqChng);
    input Fg_CLK;
    input RESETn;
    input Rot_A;
    input Rot_B;
    input Rot_C;

    output reg [11:0] Address; // 0-1800
    output reg FreqChng;

    reg [11:0] count; // 0-1800 [10:0]can over flow, 0-100 =-99 
    reg [1:0] step_exp; // 0->1, 1->10, 2->100
    reg [1:0] state; //  minus, idle, plus

    reg A1;
    reg A2;
    reg A3;
    reg A_pulse;
    reg B1;
    reg B2;
    reg B3;
    reg B_pulse;
    reg [21:0] counter;
    reg counter_pulse;
    // parameter counter_100ms = 2400000;// 100ms
    parameter counter_100ms = 3000;// for test

    //syn Rot_A (A1, A2) and make pulse from falling edge(A3)
    always @(negedge Fg_CLK or RESETn) begin
        if(~RESETn) begin
            A1 <= 0;
            A2 <= 0;
            A3 <= 0;
            A_pulse <= 0;
        end
        else begin 
            A1 <= Rot_A;
            A2 <= A1;
            A3 <= A2;
            A_pulse <= (~A2 & A3);
        end
    end 

    //syn Rot_B (B1, B2) and make pulse from falling edge(B3)
    always @(negedge Fg_CLK or RESETn) begin
        if(~RESETn) begin
            B1 <= 0;
            B2 <= 0;
            B3 <= 0;
            B_pulse <= 0;
        end
        else begin 
            B1 <= Rot_B;
            B2 <= B1;
            B3 <= B2;
            B_pulse <= (~B2 & B3);
        end
    end 
    

    always @(posedge Fg_CLK or negedge RESETn) begin
        if(~RESETn) begin
            state <= 2'b00;
            count <= 0;
        end
        else begin
            case (state)
                2'b10 : begin //minus
                    if (B_pulse) begin 
                        state <= 2'b00;
                        // count <= count - 10**step_exp;
                        // if ($signed(count) <= 0) count <= 0;// case count less than 0
                        if ($signed(count - 10**step_exp) >= 0) count <= count - 10**step_exp;
                        else                                    count <= 0;
                    end
                end

                2'b00 : begin //idle
                    if (A_pulse) state <= 2'b10;
                    if (B_pulse) state <= 2'b01;
                end

                2'b01 : begin //plus
                    if (A_pulse) begin 
                        state <= 2'b00;
                        // count <= count + 10**step_exp;
                        if (count + 10**step_exp <= 1800) count <= count + 10**step_exp;
                        else count <= 1800;// case count more than 1800
                    end
                end
                default : state <= 2'b00;
            endcase
        end
    end

    // button Rot_C
    always @(posedge Fg_CLK or negedge RESETn) begin
        if(~RESETn) step_exp <= 0;
        else if(Rot_C) begin 
            if(step_exp < 2) step_exp <= step_exp + 1;
            else step_exp <= 0;
        end
    end
    
    // make pulse every 100 ms
    always @(posedge Fg_CLK or negedge RESETn) begin
        if(~RESETn) begin 
            counter <= 0;
            counter_pulse <= 0;
        end
        else begin
            counter <= counter + 1; 
            if      (counter == counter_100ms -1)   counter_pulse <= 1;
            else if (counter >= counter_100ms) begin
                counter <= 0;
                counter_pulse <= 0; 
            end
        end
    end

    // output Address every 100 ms
    always @(posedge Fg_CLK or negedge RESETn) begin
        if      (~RESETn)       Address <= 0; 
        else if (counter_pulse) Address <= count;
    end

    // if output Adddress have change ,then this block generate pulse
    always @(posedge Fg_CLK or negedge RESETn) begin
        if(~RESETn)                                     FreqChng <= 0;
        else if ((Address != count) & counter_pulse )   FreqChng <= 1;
        else                                            FreqChng <= 0;
    end
endmodule

01_vsim/01_testbench/rotary_tb.v
`timescale 1ps/1ps

module rotary_tb();

    // ----------- registers -----------
    reg Fg_CLK_tb = 0;
    reg RESETn_tb = 0;
    reg Rot_A_i = 1;
    reg Rot_B_i = 1;
    reg Rot_C_i = 0;
    
    // ----------- wires -----------
    wire [11:0] Adddress_o;
    wire FreqChng_o;

    // ----------- device under test -----------
    rotary rotary_module (
        .Fg_CLK (Fg_CLK_tb), 
        .RESETn (RESETn_tb), 
        .Rot_A  (Rot_A_i), 
        .Rot_B  (Rot_B_i), 
        .Rot_C  (Rot_C_i), 
        
        .Address    (Adddress_o), 
        .FreqChng   (FreqChng_o)
    );

    // ----------- system signal generator-----------
    always #(41_666/2) Fg_CLK_tb = ~Fg_CLK_tb; //24M

    // ----------- test scenarios -----------
    initial begin
        repeat(100)@(posedge Fg_CLK_tb);
        RESETn_tb <= 1;
        repeat(100)@(posedge Fg_CLK_tb);
        $display("Starting test");
        Rot_A_i <=0 ;
        repeat(100)@(posedge Fg_CLK_tb);
        Rot_B_i <= 0;
        repeat(100)@(posedge Fg_CLK_tb);
        Rot_A_i <= 1;
        repeat(100)@(posedge Fg_CLK_tb);
        Rot_B_i <= 1; 

        repeat(500)@(posedge Fg_CLK_tb);
        Rot_A_i <=0 ;
        repeat(100)@(posedge Fg_CLK_tb);
        Rot_B_i <= 0;
        repeat(100)@(posedge Fg_CLK_tb);
        Rot_A_i <= 1;
        repeat(100)@(posedge Fg_CLK_tb);
        Rot_B_i <= 1; 

    repeat(500)@(posedge Fg_CLK_tb);
        Rot_B_i <=0 ;
        repeat(100)@(posedge Fg_CLK_tb);
        Rot_A_i <= 0;
        repeat(100)@(posedge Fg_CLK_tb);
        Rot_B_i <= 1;
        repeat(100)@(posedge Fg_CLK_tb);
        Rot_A_i <= 1; 
        repeat(1000)@(posedge Fg_CLK_tb);
    //plus
    repeat(100)@(posedge Fg_CLK_tb);
        Rot_B_i <=0 ;
        repeat(100)@(posedge Fg_CLK_tb);
        Rot_A_i <= 0;
        repeat(100)@(posedge Fg_CLK_tb);
        Rot_B_i <= 1;
        repeat(100)@(posedge Fg_CLK_tb);
        Rot_A_i <= 1; 
        repeat(1000)@(posedge Fg_CLK_tb);

    //test Rot_C can loop and increat follow condition
        Rot_C_i <= 1;
        repeat(1)@(posedge Fg_CLK_tb);
        Rot_C_i <= 0;
    repeat(100)@(posedge Fg_CLK_tb);
        Rot_C_i <= 1;
        repeat(1)@(posedge Fg_CLK_tb);
        Rot_C_i <= 0;
    repeat(100)@(posedge Fg_CLK_tb);
        Rot_C_i <= 1;
        repeat(1)@(posedge Fg_CLK_tb);
        Rot_C_i <= 0;
    repeat(100)@(posedge Fg_CLK_tb);
        Rot_C_i <= 1;
        repeat(1)@(posedge Fg_CLK_tb);
        Rot_C_i <= 0;
    repeat(100)@(posedge Fg_CLK_tb);
        Rot_C_i <= 1;
        repeat(1)@(posedge Fg_CLK_tb);
        Rot_C_i <= 0;
    repeat(100)@(posedge Fg_CLK_tb);


    //plus
    repeat(100)@(posedge Fg_CLK_tb);
        Rot_B_i <=0 ;
        repeat(100)@(posedge Fg_CLK_tb);
        Rot_A_i <= 0;
        repeat(100)@(posedge Fg_CLK_tb);
        Rot_B_i <= 1;
        repeat(100)@(posedge Fg_CLK_tb);
        Rot_A_i <= 1; 
        //Rot C
        Rot_C_i <= 1;
        repeat(1)@(posedge Fg_CLK_tb);
        Rot_C_i <= 0;

    repeat(100)@(posedge Fg_CLK_tb);
        Rot_C_i <= 1;
        repeat(1)@(posedge Fg_CLK_tb);
        Rot_C_i <= 0;
    repeat(100)@(posedge Fg_CLK_tb);
        
        //minus
        Rot_A_i <=0 ;
        repeat(100)@(posedge Fg_CLK_tb);
        Rot_B_i <= 0;
        repeat(100)@(posedge Fg_CLK_tb);
        Rot_A_i <= 1;
        repeat(100)@(posedge Fg_CLK_tb);
        Rot_B_i <= 1; 
    repeat(100)@(posedge Fg_CLK_tb);
        //Rot C
        Rot_C_i <= 1;
        repeat(1)@(posedge Fg_CLK_tb);
        Rot_C_i <= 0;
    repeat(10)@(posedge Fg_CLK_tb);
        //minus
        Rot_A_i <=0 ;
        repeat(100)@(posedge Fg_CLK_tb);
        Rot_B_i <= 0;
        repeat(100)@(posedge Fg_CLK_tb);
        Rot_A_i <= 1;
        repeat(100)@(posedge Fg_CLK_tb);
        Rot_B_i <= 1; 
    repeat(100)@(posedge Fg_CLK_tb);

    //plus
    repeat(100)@(posedge Fg_CLK_tb);
        Rot_B_i <=0 ;
        repeat(100)@(posedge Fg_CLK_tb);
        Rot_A_i <= 0;
        repeat(100)@(posedge Fg_CLK_tb);
        Rot_B_i <= 1;
        repeat(100)@(posedge Fg_CLK_tb);
        Rot_A_i <= 1; 

        //Rot C
        Rot_C_i <= 1;
        repeat(1)@(posedge Fg_CLK_tb);
        Rot_C_i <= 0;

    repeat(100)@(posedge Fg_CLK_tb);
        Rot_C_i <= 1;
        repeat(1)@(posedge Fg_CLK_tb);
        Rot_C_i <= 0;
    repeat(100)@(posedge Fg_CLK_tb);
        /////////////////////////
        //minus
        Rot_A_i <=0 ;
        repeat(100)@(posedge Fg_CLK_tb);
        Rot_B_i <= 0;
        repeat(100)@(posedge Fg_CLK_tb);
        Rot_A_i <= 1;
        repeat(100)@(posedge Fg_CLK_tb);
        Rot_B_i <= 1; 
    repeat(100)@(posedge Fg_CLK_tb);
    //Rot C
        Rot_C_i <= 1;
        repeat(1)@(posedge Fg_CLK_tb);
        Rot_C_i <= 0;

    repeat(100)@(posedge Fg_CLK_tb);
        Rot_C_i <= 1;
        repeat(1)@(posedge Fg_CLK_tb);
        Rot_C_i <= 0;
    repeat(100)@(posedge Fg_CLK_tb);
        
        //minus
        Rot_A_i <=0 ;
        repeat(100)@(posedge Fg_CLK_tb);
        Rot_B_i <= 0;
        repeat(100)@(posedge Fg_CLK_tb);
        Rot_A_i <= 1;
        repeat(100)@(posedge Fg_CLK_tb);
        Rot_B_i <= 1; 
    repeat(100)@(posedge Fg_CLK_tb);
    //Rot C
        Rot_C_i <= 1;
        repeat(1)@(posedge Fg_CLK_tb);
        Rot_C_i <= 0;

    repeat(100)@(posedge Fg_CLK_tb);
        Rot_C_i <= 1;
        repeat(1)@(posedge Fg_CLK_tb);
        Rot_C_i <= 0;
    repeat(100)@(posedge Fg_CLK_tb);
        
        //minus
        Rot_A_i <=0 ;
        repeat(100)@(posedge Fg_CLK_tb);
        Rot_B_i <= 0;
        repeat(100)@(posedge Fg_CLK_tb);
        Rot_A_i <= 1;
        repeat(100)@(posedge Fg_CLK_tb);
        Rot_B_i <= 1; 
    repeat(100)@(posedge Fg_CLK_tb);
    //Rot C
        Rot_C_i <= 1;
        repeat(1)@(posedge Fg_CLK_tb);
        Rot_C_i <= 0;

    repeat(100)@(posedge Fg_CLK_tb);
        Rot_C_i <= 1;
        repeat(1)@(posedge Fg_CLK_tb);
        Rot_C_i <= 0;
    repeat(100)@(posedge Fg_CLK_tb);
        
        //minus
        Rot_A_i <=0 ;
        repeat(100)@(posedge Fg_CLK_tb);
        Rot_B_i <= 0;
        repeat(100)@(posedge Fg_CLK_tb);
        Rot_A_i <= 1;
        repeat(100)@(posedge Fg_CLK_tb);
        Rot_B_i <= 1; 
    repeat(100)@(posedge Fg_CLK_tb);
    //Rot C
        Rot_C_i <= 1;
        repeat(1)@(posedge Fg_CLK_tb);
        Rot_C_i <= 0;

    repeat(100)@(posedge Fg_CLK_tb);
        Rot_C_i <= 1;
        repeat(1)@(posedge Fg_CLK_tb);
        Rot_C_i <= 0;
    repeat(100)@(posedge Fg_CLK_tb);
        
        //minus
        Rot_A_i <=0 ;
        repeat(100)@(posedge Fg_CLK_tb);
        Rot_B_i <= 0;
        repeat(100)@(posedge Fg_CLK_tb);
        Rot_A_i <= 1;
        repeat(100)@(posedge Fg_CLK_tb);
        Rot_B_i <= 1; 
    repeat(500)@(posedge Fg_CLK_tb);



//Rot C
        Rot_C_i <= 1;
        repeat(1)@(posedge Fg_CLK_tb);
        Rot_C_i <= 0;
repeat(100)@(posedge Fg_CLK_tb);
//plus
        Rot_B_i <=0 ;
        repeat(100)@(posedge Fg_CLK_tb);
        Rot_A_i <= 0;
        repeat(100)@(posedge Fg_CLK_tb);
        Rot_B_i <= 1;
        repeat(100)@(posedge Fg_CLK_tb);
        Rot_A_i <= 1; 
        repeat(200)@(posedge Fg_CLK_tb);

        //Rot C
        Rot_C_i <= 1;
        repeat(1)@(posedge Fg_CLK_tb);
        Rot_C_i <= 0;
repeat(100)@(posedge Fg_CLK_tb);
//plus
        Rot_B_i <=0 ;
        repeat(100)@(posedge Fg_CLK_tb);
        Rot_A_i <= 0;
        repeat(100)@(posedge Fg_CLK_tb);
        Rot_B_i <= 1;
        repeat(100)@(posedge Fg_CLK_tb);
        Rot_A_i <= 1; 
        repeat(200)@(posedge Fg_CLK_tb);


        //Rot C
        Rot_C_i <= 1;
        repeat(1)@(posedge Fg_CLK_tb);
        Rot_C_i <= 0;
repeat(100)@(posedge Fg_CLK_tb);
//plus
        Rot_B_i <=0 ;
        repeat(100)@(posedge Fg_CLK_tb);
        Rot_A_i <= 0;
        repeat(100)@(posedge Fg_CLK_tb);
        Rot_B_i <= 1;
        repeat(100)@(posedge Fg_CLK_tb);
        Rot_A_i <= 1; 
        repeat(200)@(posedge Fg_CLK_tb);


        //Rot C
        Rot_C_i <= 1;
        repeat(1)@(posedge Fg_CLK_tb);
        Rot_C_i <= 0;
repeat(100)@(posedge Fg_CLK_tb);
//plus
        Rot_B_i <=0 ;
        repeat(100)@(posedge Fg_CLK_tb);
        Rot_A_i <= 0;
        repeat(100)@(posedge Fg_CLK_tb);
        Rot_B_i <= 1;
        repeat(100)@(posedge Fg_CLK_tb);
        Rot_A_i <= 1; 
        repeat(200)@(posedge Fg_CLK_tb);


        //Rot C
        Rot_C_i <= 1;
        repeat(1)@(posedge Fg_CLK_tb);
        Rot_C_i <= 0;
repeat(100)@(posedge Fg_CLK_tb);
//plus
        Rot_B_i <=0 ;
        repeat(100)@(posedge Fg_CLK_tb);
        Rot_A_i <= 0;
        repeat(100)@(posedge Fg_CLK_tb);
        Rot_B_i <= 1;
        repeat(100)@(posedge Fg_CLK_tb);
        Rot_A_i <= 1; 
        repeat(200)@(posedge Fg_CLK_tb);

        //Rot C
        Rot_C_i <= 1;
        repeat(1)@(posedge Fg_CLK_tb);
        Rot_C_i <= 0;
repeat(100)@(posedge Fg_CLK_tb);
//plus
        Rot_B_i <=0 ;
        repeat(100)@(posedge Fg_CLK_tb);
        Rot_A_i <= 0;
        repeat(100)@(posedge Fg_CLK_tb);
        Rot_B_i <= 1;
        repeat(100)@(posedge Fg_CLK_tb);
        Rot_A_i <= 1; 
        repeat(200)@(posedge Fg_CLK_tb);
//Rot C
        Rot_C_i <= 1;
        repeat(1)@(posedge Fg_CLK_tb);
        Rot_C_i <= 0;
repeat(100)@(posedge Fg_CLK_tb);
//Rot C
        Rot_C_i <= 1;
        repeat(1)@(posedge Fg_CLK_tb);
        Rot_C_i <= 0;
repeat(100)@(posedge Fg_CLK_tb);
//plus
        Rot_B_i <=0 ;
        repeat(100)@(posedge Fg_CLK_tb);
        Rot_A_i <= 0;
        repeat(100)@(posedge Fg_CLK_tb);
        Rot_B_i <= 1;
        repeat(100)@(posedge Fg_CLK_tb);
        Rot_A_i <= 1; 
        repeat(200)@(posedge Fg_CLK_tb);
       
        
        //plus
        repeat(25)begin
            Rot_B_i <=0 ;
            repeat(100)@(posedge Fg_CLK_tb);
            Rot_A_i <= 0;
            repeat(100)@(posedge Fg_CLK_tb);
            Rot_B_i <= 1;
            repeat(100)@(posedge Fg_CLK_tb);
            Rot_A_i <= 1; 
            repeat(200)@(posedge Fg_CLK_tb);
        end

repeat(10)begin
            //Rot C
            Rot_C_i <= 1;
            repeat(1)@(posedge Fg_CLK_tb);
            Rot_C_i <= 0;
            repeat(10)@(posedge Fg_CLK_tb)
        repeat(100)@(posedge Fg_CLK_tb);
    //pluss
            Rot_B_i <=0 ;
            repeat(100)@(posedge Fg_CLK_tb);
            Rot_A_i <= 0;
            repeat(100)@(posedge Fg_CLK_tb);
            Rot_B_i <= 1;
            repeat(100)@(posedge Fg_CLK_tb);
            Rot_A_i <= 1; 
            repeat(200)@(posedge Fg_CLK_tb);
        end


        repeat(15)begin
            //Rot C
            Rot_C_i <= 1;
            repeat(1)@(posedge Fg_CLK_tb);
            Rot_C_i <= 0;
            repeat(10)@(posedge Fg_CLK_tb)
        repeat(100)@(posedge Fg_CLK_tb);
    //minus
            Rot_A_i <=0 ;
            repeat(100)@(posedge Fg_CLK_tb);
            Rot_B_i <= 0;
            repeat(100)@(posedge Fg_CLK_tb);
            Rot_A_i <= 1;
            repeat(100)@(posedge Fg_CLK_tb);
            Rot_B_i <= 1; 
            repeat(200)@(posedge Fg_CLK_tb);

        end
        repeat(2)begin
            //Rot C
            Rot_C_i <= 1;
            repeat(1)@(posedge Fg_CLK_tb);
            Rot_C_i <= 0;
            repeat(10)@(posedge Fg_CLK_tb)
            repeat(100)@(posedge Fg_CLK_tb);
        end

        //minus
        repeat(25)begin
            Rot_A_i <=0 ;
            repeat(100)@(posedge Fg_CLK_tb);
            Rot_B_i <= 0;
            repeat(100)@(posedge Fg_CLK_tb);
            Rot_A_i <= 1;
            repeat(100)@(posedge Fg_CLK_tb);
            Rot_B_i <= 1; 
            repeat(200)@(posedge Fg_CLK_tb);
        end
        
        repeat(1000)@(posedge Fg_CLK_tb);$stop;

    end

    // ----------- dumping wave -----------
    initial begin
        $dumpfile("rotary_tb.vcd");
        $dumpvars(0,rotary_tb);
    end
endmodule

01_vsim/rotary_tb.vcd
$date
	Sat Jun 22 16:15:03 2024
$end
$version
	ModelSim Version 2020.1
$end
$timescale
	1ps
$end

$scope module rotary_tb $end
$var reg 1 ! Fg_CLK_tb $end
$var reg 1 " RESETn_tb $end
$var reg 1 # Rot_A_i $end
$var reg 1 $ Rot_B_i $end
$var reg 1 % Rot_C_i $end
$var wire 1 & Adddress_o [11] $end
$var wire 1 ' Adddress_o [10] $end
$var wire 1 ( Adddress_o [9] $end
$var wire 1 ) Adddress_o [8] $end
$var wire 1 * Adddress_o [7] $end
$var wire 1 + Adddress_o [6] $end
$var wire 1 , Adddress_o [5] $end
$var wire 1 - Adddress_o [4] $end
$var wire 1 . Adddress_o [3] $end
$var wire 1 / Adddress_o [2] $end
$var wire 1 0 Adddress_o [1] $end
$var wire 1 1 Adddress_o [0] $end
$var wire 1 2 FreqChng_o $end

$scope module rotary_module $end
$var parameter 32 3 counter_100ms $end
$var wire 1 4 Fg_CLK $end
$var wire 1 5 RESETn $end
$var wire 1 6 Rot_A $end
$var wire 1 7 Rot_B $end
$var wire 1 8 Rot_C $end
$var reg 12 9 Address [11:0] $end
$var reg 1 : FreqChng $end
$var reg 12 ; count [11:0] $end
$var reg 2 < step_exp [1:0] $end
$var reg 2 = state [1:0] $end
$var reg 1 > A1 $end
$var reg 1 ? A2 $end
$var reg 1 @ A3 $end
$var reg 1 A A_pulse $end
$var reg 1 B B1 $end
$var reg 1 C B2 $end
$var reg 1 D B3 $end
$var reg 1 E B_pulse $end
$var reg 22 F counter [21:0] $end
$var reg 1 G counter_pulse $end
$upscope $end
$upscope $end
$enddefinitions $end
#0
$dumpvars
0!
0"
1#
1$
0%
b0 9
0:
b0 ;
b0 <
b0 =
0>
0?
0@
0A
0B
0C
0D
0E
b0 F
0G
b101110111000 3
01
00
0/
0.
0-
0,
0+
0*
0)
0(
0'
0&
02
08
17
16
05
04
$end
#20833
1!
14
#41666
0!
04
#62499
1!
14
#83332
0!
04
#104165
1!
14
#124998
0!
04
#145831
1!
14
#166664
0!
04
#187497
1!
14
#208330
0!
04
#229163
1!
14
#249996
0!
04
#270829
1!
14
#291662
0!
04
#312495
1!
14
#333328
0!
04
#354161
1!
14
#374994
0!
04
#395827
1!
14
#416660
0!
04
#437493
1!
14
#458326
0!
04
#479159
1!
14
#499992
0!
04
#520825
1!
14
#541658
0!
04
#562491
1!
14
#583324
0!
04
#604157
1!
14
#624990
0!
04
#645823
1!
14
#666656
0!
04
#687489
1!
14
#708322
0!
04
#729155
1!
14
#749988
0!
04
#770821
1!
14
#791654
0!
04
#812487
1!
14
#833320
0!
04
#854153
1!
14
#874986
0!
04
#895819
1!
14
#916652
0!
04
#937485
1!
14
#958318
0!
04
#979151
1!
14
#999984
0!
04
#1020817
1!
14
#1041650
0!
04
#1062483
1!
14
#1083316
0!
04
#1104149
1!
14
#1124982
0!
04
#1145815
1!
14
#1166648
0!
04
#1187481
1!
14
#1208314
0!
04
#1229147
1!
14
#1249980
0!
04
#1270813
1!
14
#1291646
0!
04
#1312479
1!
14
#1333312
0!
04
#1354145
1!
14
#1374978
0!
04
#1395811
1!
14
#1416644
0!
04
#1437477
1!
14
#1458310
0!
04
#1479143
1!
14
#1499976
0!
04
#1520809
1!
14
#1541642
0!
04
#1562475
1!
14
#1583308
0!
04
#1604141
1!
14
#1624974
0!
04
#1645807
1!
14
#1666640
0!
04
#1687473
1!
14
#1708306
0!
04
#1729139
1!
14
#1749972
0!
04
#1770805
1!
14
#1791638
0!
04
#1812471
1!
14
#1833304
0!
04
#1854137
1!
14
#1874970
0!
04
#1895803
1!
14
#1916636
0!
04
#1937469
1!
14
#1958302
0!
04
#1979135
1!
14
#1999968
0!
04
#2020801
1!
14
#2041634
0!
04
#2062467
1!
14
#2083300
0!
04
#2104133
1!
14
#2124966
0!
04
#2145799
1!
14
#2166632
0!
04
#2187465
1!
14
#2208298
0!
04
#2229131
1!
14
#2249964
0!
04
#2270797
1!
14
#2291630
0!
04
#2312463
1!
14
#2333296
0!
04
#2354129
1!
14
#2374962
0!
04
#2395795
1!
14
#2416628
0!
04
#2437461
1!
14
#2458294
0!
04
#2479127
1!
14
#2499960
0!
04
#2520793
1!
14
#2541626
0!
04
#2562459
1!
14
#2583292
0!
04
#2604125
1!
14
#2624958
0!
04
#2645791
1!
14
#2666624
0!
04
#2687457
1!
14
#2708290
0!
04
#2729123
1!
14
#2749956
0!
04
#2770789
1!
14
#2791622
0!
04
#2812455
1!
14
#2833288
0!
04
#2854121
1!
14
#2874954
0!
04
#2895787
1!
14
#2916620
0!
04
#2937453
1!
14
#2958286
0!
04
#2979119
1!
14
#2999952
0!
04
#3020785
1!
14
#3041618
0!
04
#3062451
1!
14
#3083284
0!
04
#3104117
1!
14
#3124950
0!
04
#3145783
1!
14
#3166616
0!
04
#3187449
1!
14
#3208282
0!
04
#3229115
1!
14
#3249948
0!
04
#3270781
1!
14
#3291614
0!
04
#3312447
1!
14
#3333280
0!
04
#3354113
1!
14
#3374946
0!
04
#3395779
1!
14
#3416612
0!
04
#3437445
1!
14
#3458278
0!
04
#3479111
1!
14
#3499944
0!
04
#3520777
1!
14
#3541610
0!
04
#3562443
1!
14
#3583276
0!
04
#3604109
1!
14
#3624942
0!
04
#3645775
1!
14
#3666608
0!
04
#3687441
1!
14
#3708274
0!
04
#3729107
1!
14
#3749940
0!
04
#3770773
1!
14
#3791606
0!
04
#3812439
1!
14
#3833272
0!
04
#3854105
1!
14
#3874938
0!
04
#3895771
1!
14
#3916604
0!
04
#3937437
1!
14
#3958270
0!
04
#3979103
1!
14
#3999936
0!
04
#4020769
1!
14
#4041602
0!
04
#4062435
1!
14
#4083268
0!
04
#4104101
1!
14
#4124934
0!
04
#4145767
1!
14
1"
15
1>
1B
#4166600
0!
04
1?
1C
#4187433
1!
14
b1 F
#4208266
0!
04
1@
1D
#4229099
1!
14
b10 F
#4249932
0!
04
#4270765
1!
14
b11 F
#4291598
0!
04
#4312431
1!
14
b100 F
#4333264
0!
04
#4354097
1!
14
b101 F
#4374930
0!
04
#4395763
1!
14
b110 F
#4416596
0!
04
#4437429
1!
14
b111 F
#4458262
0!
04
#4479095
1!
14
b1000 F
#4499928
0!
04
#4520761
1!
14
b1001 F
#4541594
0!
04
#4562427
1!
14
b1010 F
#4583260
0!
04
#4604093
1!
14
b1011 F
#4624926
0!
04
#4645759
1!
14
b1100 F
#4666592
0!
04
#4687425
1!
14
b1101 F
#4708258
0!
04
#4729091
1!
14
b1110 F
#4749924
0!
04
#4770757
1!
14
b1111 F
#4791590
0!
04
#4812423
1!
14
b10000 F
#4833256
0!
04
#4854089
1!
14
b10001 F
#4874922
0!
04
#4895755
1!
14
b10010 F
#4916588
0!
04
#4937421
1!
14
b10011 F
#4958254
0!
04
#4979087
1!
14
b10100 F
#4999920
0!
04
#5020753
1!
14
b10101 F
#5041586
0!
04
#5062419
1!
14
b10110 F
#5083252
0!
04
#5104085
1!
14
b10111 F
#5124918
0!
04
#5145751
1!
14
b11000 F
#5166584
0!
04
#5187417
1!
14
b11001 F
#5208250
0!
04
#5229083
1!
14
b11010 F
#5249916
0!
04
#5270749
1!
14
b11011 F
#5291582
0!
04
#5312415
1!
14
b11100 F
#5333248
0!
04
#5354081
1!
14
b11101 F
#5374914
0!
04
#5395747
1!
14
b11110 F
#5416580
0!
04
#5437413
1!
14
b11111 F
#5458246
0!
04
#5479079
1!
14
b100000 F
#5499912
0!
04
#5520745
1!
14
b100001 F
#5541578
0!
04
#5562411
1!
14
b100010 F
#5583244
0!
04
#5604077
1!
14
b100011 F
#5624910
0!
04
#5645743
1!
14
b100100 F
#5666576
0!
04
#5687409
1!
14
b100101 F
#5708242
0!
04
#5729075
1!
14
b100110 F
#5749908
0!
04
#5770741
1!
14
b100111 F
#5791574
0!
04
#5812407
1!
14
b101000 F
#5833240
0!
04
#5854073
1!
14
b101001 F
#5874906
0!
04
#5895739
1!
14
b101010 F
#5916572
0!
04
#5937405
1!
14
b101011 F
#5958238
0!
04
#5979071
1!
14
b101100 F
#5999904
0!
04
#6020737
1!
14
b101101 F
#6041570
0!
04
#6062403
1!
14
b101110 F
#6083236
0!
04
#6104069
1!
14
b101111 F
#6124902
0!
04
#6145735
1!
14
b110000 F
#6166568
0!
04
#6187401
1!
14
b110001 F
#6208234
0!
04
#6229067
1!
14
b110010 F
#6249900
0!
04
#6270733
1!
14
b110011 F
#6291566
0!
04
#6312399
1!
14
b110100 F
#6333232
0!
04
#6354065
1!
14
b110101 F
#6374898
0!
04
#6395731
1!
14
b110110 F
#6416564
0!
04
#6437397
1!
14
b110111 F
#6458230
0!
04
#6479063
1!
14
b111000 F
#6499896
0!
04
#6520729
1!
14
b111001 F
#6541562
0!
04
#6562395
1!
14
b111010 F
#6583228
0!
04
#6604061
1!
14
b111011 F
#6624894
0!
04
#6645727
1!
14
b111100 F
#6666560
0!
04
#6687393
1!
14
b111101 F
#6708226
0!
04
#6729059
1!
14
b111110 F
#6749892
0!
04
#6770725
1!
14
b111111 F
#6791558
0!
04
#6812391
1!
14
b1000000 F
#6833224
0!
04
#6854057
1!
14
b1000001 F
#6874890
0!
04
#6895723
1!
14
b1000010 F
#6916556
0!
04
#6937389
1!
14
b1000011 F
#6958222
0!
04
#6979055
1!
14
b1000100 F
#6999888
0!
04
#7020721
1!
14
b1000101 F
#7041554
0!
04
#7062387
1!
14
b1000110 F
#7083220
0!
04
#7104053
1!
14
b1000111 F
#7124886
0!
04
#7145719
1!
14
b1001000 F
#7166552
0!
04
#7187385
1!
14
b1001001 F
#7208218
0!
04
#7229051
1!
14
b1001010 F
#7249884
0!
04
#7270717
1!
14
b1001011 F
#7291550
0!
04
#7312383
1!
14
b1001100 F
#7333216
0!
04
#7354049
1!
14
b1001101 F
#7374882
0!
04
#7395715
1!
14
b1001110 F
#7416548
0!
04
#7437381
1!
14
b1001111 F
#7458214
0!
04
#7479047
1!
14
b1010000 F
#7499880
0!
04
#7520713
1!
14
b1010001 F
#7541546
0!
04
#7562379
1!
14
b1010010 F
#7583212
0!
04
#7604045
1!
14
b1010011 F
#7624878
0!
04
#7645711
1!
14
b1010100 F
#7666544
0!
04
#7687377
1!
14
b1010101 F
#7708210
0!
04
#7729043
1!
14
b1010110 F
#7749876
0!
04
#7770709
1!
14
b1010111 F
#7791542
0!
04
#7812375
1!
14
b1011000 F
#7833208
0!
04
#7854041
1!
14
b1011001 F
#7874874
0!
04
#7895707
1!
14
b1011010 F
#7916540
0!
04
#7937373
1!
14
b1011011 F
#7958206
0!
04
#7979039
1!
14
b1011100 F
#7999872
0!
04
#8020705
1!
14
b1011101 F
#8041538
0!
04
#8062371
1!
14
b1011110 F
#8083204
0!
04
#8104037
1!
14
b1011111 F
#8124870
0!
04
#8145703
1!
14
b1100000 F
#8166536
0!
04
#8187369
1!
14
b1100001 F
#8208202
0!
04
#8229035
1!
14
b1100010 F
#8249868
0!
04
#8270701
1!
14
b1100011 F
#8291534
0!
04
#8312367
1!
14
b1100100 F
0#
06
#8333200
0!
04
0>
#8354033
1!
14
b1100101 F
#8374866
0!
04
0?
#8395699
1!
14
b1100110 F
#8416532
0!
04
0@
1A
#8437365
1!
14
b10 =
b1100111 F
#8458198
0!
04
0A
#8479031
1!
14
b1101000 F
#8499864
0!
04
#8520697
1!
14
b1101001 F
#8541530
0!
04
#8562363
1!
14
b1101010 F
#8583196
0!
04
#8604029
1!
14
b1101011 F
#8624862
0!
04
#8645695
1!
14
b1101100 F
#8666528
0!
04
#8687361
1!
14
b1101101 F
#8708194
0!
04
#8729027
1!
14
b1101110 F
#8749860
0!
04
#8770693
1!
14
b1101111 F
#8791526
0!
04
#8812359
1!
14
b1110000 F
#8833192
0!
04
#8854025
1!
14
b1110001 F
#8874858
0!
04
#8895691
1!
14
b1110010 F
#8916524
0!
04
#8937357
1!
14
b1110011 F
#8958190
0!
04
#8979023
1!
14
b1110100 F
#8999856
0!
04
#9020689
1!
14
b1110101 F
#9041522
0!
04
#9062355
1!
14
b1110110 F
#9083188
0!
04
#9104021
1!
14
b1110111 F
#9124854
0!
04
#9145687
1!
14
b1111000 F
#9166520
0!
04
#9187353
1!
14
b1111001 F
#9208186
0!
04
#9229019
1!
14
b1111010 F
#9249852
0!
04
#9270685
1!
14
b1111011 F
#9291518
0!
04
#9312351
1!
14
b1111100 F
#9333184
0!
04
#9354017
1!
14
b1111101 F
#9374850
0!
04
#9395683
1!
14
b1111110 F
#9416516
0!
04
#9437349
1!
14
b1111111 F
#9458182
0!
04
#9479015
1!
14
b10000000 F
#9499848
0!
04
#9520681
1!
14
b10000001 F
#9541514
0!
04
#9562347
1!
14
b10000010 F
#9583180
0!
04
#9604013
1!
14
b10000011 F
#9624846
0!
04
#9645679
1!
14
b10000100 F
#9666512
0!
04
#9687345
1!
14
b10000101 F
#9708178
0!
04
