00_source/sampling_control.v
module sampling_control(Fg_CLK,RESETn,IntBTN,Ready,Enable,Mode);
    input Fg_CLK;
    input RESETn;
    input IntBTN;

    output Ready;
    output reg Enable;
    output reg [3:0] Mode; // 5 mode (0-4)

    reg [14:0] counter_Enable;
    reg [6:0] counter_Ready;
    reg reg_pulse;// pulse in

    //----- counter mode --------
    always @(posedge Fg_CLK or negedge RESETn)begin 
        if(~RESETn)begin
            Mode <= 0;
        end
        else if (reg_pulse && Enable)begin
            if(Mode < 4 )begin
                Mode <= Mode +1;
            end
            else begin
                Mode <= 0;
            end
            reg_pulse <= 0;
        end
    end

    //---------- general Enable sinal -------------
    always @(posedge Fg_CLK or negedge RESETn)begin 
        if(~RESETn)begin
            Enable <= 1;
            counter_Enable <= 0;
        end
        else begin
            counter_Enable <= counter_Enable + 1;

            if(counter_Enable >= 10**Mode-1) begin
                Enable <= 1;
                counter_Enable <= 0;
            end
            else begin
                Enable <= 0;
            end
        end
    end

    //------------- counter ready ------------
    always @(posedge Fg_CLK or negedge RESETn)begin
        if(~RESETn)begin
            counter_Ready <= 0;
        end
        else if (counter_Ready < 80) begin
            counter_Ready <= counter_Ready + 1;
        end
    end

    //------------- reg_pulse ------------
    always @(posedge Fg_CLK or negedge RESETn)begin
        if(~RESETn)begin
            reg_pulse <= 0;
        end
        else if (IntBTN) begin
            reg_pulse <=1;
        end
        
    end
endmodule

01_vsim/01_testbench/sampling_control_tb.v
`timescale 1ps/1ps

module sampling_control_tb();

    // ----------- registers -----------
    reg Fg_CLK_i = 0;
    reg RESETn_i = 0;
    reg IntBTN_i = 0;
    
    // ----------- wires -----------
    wire Ready_o;
    wire Enable_o;
    wire [3:0] Mode_o;
    
    // ----------- device under test -----------
    sampling_control samp_module(
        .Fg_CLK(Fg_CLK_i),
        .RESETn(RESETn_i),
        .IntBTN(IntBTN_i),
        .Ready(Ready_o),
        .Enable(Enable_o),
        .Mode(Mode_o)
    );

    // ----------- system signal generator-----------
    always #(41_666) Fg_CLK_i = ~Fg_CLK_i; //24M

    // ----------- test scenarios -----------
    initial begin
        repeat(10)@(posedge Fg_CLK_i);
        RESETn_i <= 1;
        repeat(10)@(posedge Fg_CLK_i);
        $display("Starting test");
        repeat(1)@(posedge Fg_CLK_i);
        IntBTN_i <= 1;
        repeat(1)@(posedge Fg_CLK_i);
        IntBTN_i <= 0;
        repeat(1000)@(posedge Fg_CLK_i);

        repeat(1)@(posedge Fg_CLK_i);
        IntBTN_i <= 1;
        repeat(1)@(posedge Fg_CLK_i);
        IntBTN_i <= 0;
        repeat(1000)@(posedge Fg_CLK_i);

        repeat(1)@(posedge Fg_CLK_i);
        IntBTN_i <= 1;
        repeat(1)@(posedge Fg_CLK_i);
        IntBTN_i <= 0;
        repeat(10000)@(posedge Fg_CLK_i);

        //test loop mode
        repeat(1)@(posedge Fg_CLK_i);
        IntBTN_i <= 1;
        repeat(1)@(posedge Fg_CLK_i);
        IntBTN_i <= 0;
        repeat(100)@(posedge Fg_CLK_i);

        repeat(1)@(posedge Fg_CLK_i);
        IntBTN_i <= 1;
        repeat(1)@(posedge Fg_CLK_i);
        IntBTN_i <= 0;
        repeat(100)@(posedge Fg_CLK_i);
        repeat(1)@(posedge Fg_CLK_i);
        IntBTN_i <= 1;
        repeat(1)@(posedge Fg_CLK_i);
        IntBTN_i <= 0;
        repeat(100)@(posedge Fg_CLK_i);
        repeat(1)@(posedge Fg_CLK_i);
        IntBTN_i <= 1;
        repeat(1)@(posedge Fg_CLK_i);
        IntBTN_i <= 0;
        repeat(100)@(posedge Fg_CLK_i);
        repeat(1)@(posedge Fg_CLK_i);
        IntBTN_i <= 1;
        repeat(1)@(posedge Fg_CLK_i);
        IntBTN_i <= 0;
        repeat(100)@(posedge Fg_CLK_i);
        repeat(1)@(posedge Fg_CLK_i);
        IntBTN_i <= 1;
        repeat(1)@(posedge Fg_CLK_i);
        IntBTN_i <= 0;
        repeat(100)@(posedge Fg_CLK_i);
        repeat(1)@(posedge Fg_CLK_i);
        IntBTN_i <= 1;
        repeat(1)@(posedge Fg_CLK_i);
        IntBTN_i <= 0;
        repeat(100)@(posedge Fg_CLK_i);
        repeat(1)@(posedge Fg_CLK_i);
        IntBTN_i <= 1;
        repeat(1)@(posedge Fg_CLK_i);
        IntBTN_i <= 0;
        repeat(100)@(posedge Fg_CLK_i);
        repeat(1)@(posedge Fg_CLK_i);
        IntBTN_i <= 1;
        repeat(1)@(posedge Fg_CLK_i);
        IntBTN_i <= 0;
        repeat(100)@(posedge Fg_CLK_i);
        repeat(1)@(posedge Fg_CLK_i);
        IntBTN_i <= 1;
        repeat(1)@(posedge Fg_CLK_i);
        IntBTN_i <= 0;
        repeat(100)@(posedge Fg_CLK_i);
        repeat(1)@(posedge Fg_CLK_i);
        IntBTN_i <= 1;
        repeat(1)@(posedge Fg_CLK_i);
        IntBTN_i <= 0;
        repeat(100)@(posedge Fg_CLK_i);
        repeat(1000)@(posedge Fg_CLK_i);
        $stop;
    end

    // ----------- dumping wave -----------
    initial begin
        $dumpfile("sampling_control_tb.vcd");
        $dumpvars(0,sampling_control_tb);
    end
endmodule

01_vsim/sampling_control_tb.vcd
$date
	Thu Jun 20 20:13:21 2024
$end
$version
	ModelSim Version 2020.1
$end
$timescale
	1ps
$end

$scope module sampling_control_tb $end
$var reg 1 ! Fg_CLK_i $end
$var reg 1 " RESETn_i $end
$var reg 1 # IntBTN_i $end
$var wire 1 $ Ready_o $end
$var wire 1 % Enable_o $end
$var wire 1 & Mode_o [3] $end
$var wire 1 ' Mode_o [2] $end
$var wire 1 ( Mode_o [1] $end
$var wire 1 ) Mode_o [0] $end

$scope module samp_module $end
$var wire 1 * Fg_CLK $end
$var wire 1 + RESETn $end
$var wire 1 , IntBTN $end
$var wire 1 $ Ready $end
$var reg 1 - Enable $end
$var reg 4 . Mode [3:0] $end
$var reg 15 / counter_Enable [14:0] $end
$var reg 7 0 counter_Ready [6:0] $end
$var reg 1 1 reg_pulse $end
$upscope $end
$upscope $end
$enddefinitions $end
#0
$dumpvars
0!
0"
0#
1-
b0 .
b0 /
b0 0
01
z$
1%
0)
0(
0'
0&
0,
0+
0*
$end
#41666
1!
1*
#83332
0!
0*
#124998
1!
1*
#166664
0!
0*
#208330
1!
1*
#249996
0!
0*
#291662
1!
1*
#333328
0!
0*
#374994
1!
1*
#416660
0!
0*
#458326
1!
1*
#499992
0!
0*
#541658
1!
1*
#583324
0!
0*
#624990
1!
1*
#666656
0!
0*
#708322
1!
1*
#749988
0!
0*
#791654
1!
1*
1"
1+
#833320
0!
0*
#874986
1!
1*
b1 /
b0 /
b1 0
#916652
0!
0*
#958318
1!
1*
b1 /
b0 /
b10 0
#999984
0!
0*
#1041650
1!
1*
b1 /
b0 /
b11 0
#1083316
0!
0*
#1124982
1!
1*
b1 /
b0 /
b100 0
#1166648
0!
0*
#1208314
1!
1*
b1 /
b0 /
b101 0
#1249980
0!
0*
#1291646
1!
1*
b1 /
b0 /
b110 0
#1333312
0!
0*
#1374978
1!
1*
b1 /
b0 /
b111 0
#1416644
0!
0*
#1458310
1!
1*
b1 /
b0 /
b1000 0
#1499976
0!
0*
#1541642
1!
1*
b1 /
b0 /
b1001 0
#1583308
0!
0*
#1624974
1!
1*
b1 /
b0 /
b1010 0
#1666640
0!
0*
#1708306
1!
1*
b1 /
b0 /
b1011 0
1#
1,
#1749972
0!
0*
#1791638
1!
1*
b1 /
b0 /
b1100 0
11
0#
0,
#1833304
0!
0*
#1874970
1!
1*
b1 .
01
b1 /
b0 /
b1101 0
1)
#1916636
0!
0*
#1958302
1!
1*
b1 /
0-
b1110 0
0%
#1999968
0!
0*
#2041634
1!
1*
b10 /
b1111 0
#2083300
0!
0*
#2124966
1!
1*
b11 /
b10000 0
#2166632
0!
0*
#2208298
1!
1*
b100 /
b10001 0
#2249964
0!
0*
#2291630
1!
1*
b101 /
b10010 0
#2333296
0!
0*
#2374962
1!
1*
b110 /
b10011 0
#2416628
0!
0*
#2458294
1!
1*
b111 /
b10100 0
#2499960
0!
0*
#2541626
1!
1*
b1000 /
b10101 0
#2583292
0!
0*
#2624958
1!
1*
b1001 /
b10110 0
#2666624
0!
0*
#2708290
1!
1*
b1010 /
1-
b0 /
b10111 0
1%
#2749956
0!
0*
#2791622
1!
1*
b1 /
0-
b11000 0
0%
#2833288
0!
0*
#2874954
1!
1*
b10 /
b11001 0
#2916620
0!
0*
#2958286
1!
1*
b11 /
b11010 0
#2999952
0!
0*
#3041618
1!
1*
b100 /
b11011 0
#3083284
0!
0*
#3124950
1!
1*
b101 /
b11100 0
#3166616
0!
0*
#3208282
1!
1*
b110 /
b11101 0
#3249948
0!
0*
#3291614
1!
1*
b111 /
b11110 0
#3333280
0!
0*
#3374946
1!
1*
b1000 /
b11111 0
#3416612
0!
0*
#3458278
1!
1*
b1001 /
b100000 0
#3499944
0!
0*
#3541610
1!
1*
b1010 /
1-
b0 /
b100001 0
1%
#3583276
0!
0*
#3624942
1!
1*
b1 /
0-
b100010 0
0%
#3666608
0!
0*
#3708274
1!
1*
b10 /
b100011 0
#3749940
0!
0*
#3791606
1!
1*
b11 /
b100100 0
#3833272
0!
0*
#3874938
1!
1*
b100 /
b100101 0
#3916604
0!
0*
#3958270
1!
1*
b101 /
b100110 0
#3999936
0!
0*
#4041602
1!
1*
b110 /
b100111 0
#4083268
0!
0*
#4124934
1!
1*
b111 /
b101000 0
#4166600
0!
0*
#4208266
1!
1*
b1000 /
b101001 0
#4249932
0!
0*
#4291598
1!
1*
b1001 /
b101010 0
#4333264
0!
0*
#4374930
1!
1*
b1010 /
1-
b0 /
b101011 0
1%
#4416596
0!
0*
#4458262
1!
1*
b1 /
0-
b101100 0
0%
#4499928
0!
0*
#4541594
1!
1*
b10 /
b101101 0
#4583260
0!
0*
#4624926
1!
1*
b11 /
b101110 0
#4666592
0!
0*
#4708258
1!
1*
b100 /
b101111 0
#4749924
0!
0*
#4791590
1!
1*
b101 /
b110000 0
#4833256
0!
0*
#4874922
1!
1*
b110 /
b110001 0
#4916588
0!
0*
#4958254
1!
1*
b111 /
b110010 0
#4999920
0!
0*
#5041586
1!
1*
b1000 /
b110011 0
#5083252
0!
0*
#5124918
1!
1*
b1001 /
b110100 0
#5166584
0!
0*
#5208250
1!
1*
b1010 /
1-
b0 /
b110101 0
1%
#5249916
0!
0*
#5291582
1!
1*
b1 /
0-
b110110 0
0%
#5333248
0!
0*
#5374914
1!
1*
b10 /
b110111 0
#5416580
0!
0*
#5458246
1!
1*
b11 /
b111000 0
#5499912
0!
0*
#5541578
1!
1*
b100 /
b111001 0
#5583244
0!
0*
#5624910
1!
1*
b101 /
b111010 0
#5666576
0!
0*
#5708242
1!
1*
b110 /
b111011 0
#5749908
0!
0*
#5791574
1!
1*
b111 /
b111100 0
#5833240
0!
0*
#5874906
1!
1*
b1000 /
b111101 0
#5916572
0!
0*
#5958238
1!
1*
b1001 /
b111110 0
#5999904
0!
0*
#6041570
1!
1*
b1010 /
1-
b0 /
b111111 0
1%
#6083236
0!
0*
#6124902
1!
1*
b1 /
0-
b1000000 0
0%
#6166568
0!
0*
#6208234
1!
1*
b10 /
b1000001 0
#6249900
0!
0*
#6291566
1!
1*
b11 /
b1000010 0
#6333232
0!
0*
#6374898
1!
1*
b100 /
b1000011 0
#6416564
0!
0*
#6458230
1!
1*
b101 /
b1000100 0
#6499896
0!
0*
#6541562
1!
1*
b110 /
b1000101 0
#6583228
0!
0*
#6624894
1!
1*
b111 /
b1000110 0
#6666560
0!
0*
#6708226
1!
1*
b1000 /
b1000111 0
#6749892
0!
0*
#6791558
1!
1*
b1001 /
b1001000 0
#6833224
0!
0*
#6874890
1!
1*
b1010 /
1-
b0 /
b1001001 0
1%
#6916556
0!
0*
#6958222
1!
1*
b1 /
0-
b1001010 0
0%
#6999888
0!
0*
#7041554
1!
1*
b10 /
b1001011 0
#7083220
0!
0*
#7124886
1!
1*
b11 /
b1001100 0
#7166552
0!
0*
#7208218
1!
1*
b100 /
b1001101 0
#7249884
0!
0*
#7291550
1!
1*
b101 /
b1001110 0
#7333216
0!
0*
#7374882
1!
1*
b110 /
b1001111 0
#7416548
0!
0*
#7458214
1!
1*
b111 /
b1010000 0
#7499880
0!
0*
#7541546
1!
1*
b1000 /
#7583212
0!
0*
#7624878
1!
1*
b1001 /
#7666544
0!
0*
#7708210
1!
1*
b1010 /
1-
b0 /
1%
#7749876
0!
0*
#7791542
1!
1*
b1 /
0-
0%
#7833208
0!
0*
#7874874
1!
1*
b10 /
#7916540
0!
0*
#7958206
1!
1*
b11 /
#7999872
0!
0*
#8041538
1!
1*
b100 /
#8083204
0!
0*
#8124870
1!
1*
b101 /
#8166536
0!
0*
#8208202
1!
1*
b110 /
#8249868
0!
0*
#8291534
1!
1*
b111 /
#8333200
0!
0*
#8374866
1!
1*
b1000 /
#8416532
0!
0*
#8458198
1!
1*
b1001 /
#8499864
0!
0*
#8541530
1!
1*
b1010 /
1-
b0 /
1%
#8583196
0!
0*
#8624862
1!
1*
b1 /
0-
0%
#8666528
0!
0*
#8708194
1!
1*
b10 /
#8749860
0!
0*
#8791526
1!
1*
b11 /
#8833192
0!
0*
#8874858
1!
1*
b100 /
#8916524
0!
0*
#8958190
1!
1*
b101 /
#8999856
0!
0*
#9041522
1!
1*
b110 /
#9083188
0!
0*
#9124854
1!
1*
b111 /
#9166520
0!
0*
#9208186
1!
1*
b1000 /
#9249852
0!
0*
#9291518
1!
1*
b1001 /
#9333184
0!
0*
#9374850
1!
1*
b1010 /
1-
b0 /
1%
#9416516
0!
0*
#9458182
1!
1*
b1 /
0-
0%
#9499848
0!
0*
#9541514
1!
1*
b10 /
#9583180
0!
0*
#9624846
1!
1*
b11 /
#9666512
0!
0*
#9708178
1!
1*
b100 /
#9749844
0!
0*
#9791510
1!
1*
b101 /
#9833176
0!
0*
#9874842
1!
1*
b110 /
#9916508
0!
0*
#9958174
1!
1*
b111 /
#9999840
0!
0*
#10041506
1!
1*
b1000 /
#10083172
0!
0*
#10124838
1!
1*
b1001 /
#10166504
0!
0*
#10208170
1!
1*
b1010 /
1-
b0 /
1%
#10249836
0!
0*
#10291502
1!
1*
b1 /
0-
0%
#10333168
0!
0*
#10374834
1!
1*
b10 /
#10416500
0!
0*
#10458166
1!
1*
b11 /
#10499832
0!
0*
#10541498
1!
1*
b100 /
#10583164
0!
0*
#10624830
1!
1*
b101 /
#10666496
0!
0*
#10708162
1!
1*
b110 /
#10749828
0!
0*
#10791494
1!
1*
b111 /
#10833160
0!
0*
#10874826
1!
1*
b1000 /
#10916492
0!
0*
#10958158
1!
1*
b1001 /
#10999824
0!
0*
#11041490
1!
1*
b1010 /
1-
b0 /
1%
#11083156
0!
0*
#11124822
1!
1*
b1 /
0-
0%
#11166488
0!
0*
#11208154
1!
1*
b10 /
#11249820
0!
0*
#11291486
1!
1*
b11 /
#11333152
0!
0*
#11374818
1!
1*
b100 /
#11416484
0!
0*
#11458150
1!
1*
b101 /
#11499816
0!
0*
#11541482
1!
1*
b110 /
#11583148
0!
0*
#11624814
1!
1*
b111 /
#11666480
0!
0*
#11708146
1!
1*
b1000 /
#11749812
0!
0*
#11791478
1!
1*
b1001 /
#11833144
0!
0*
#11874810
1!
1*
b1010 /
1-
b0 /
1%
#11916476
0!
0*
#11958142
1!
1*
b1 /
0-
0%
#11999808
0!
0*
#12041474
1!
1*
b10 /
#12083140
0!
0*
#12124806
1!
1*
b11 /
#12166472
0!
0*
#12208138
1!
1*
b100 /
#12249804
0!
0*
#12291470
1!
1*
b101 /
#12333136
0!
0*
#12374802
1!
1*
b110 /
#12416468
0!
0*
#12458134
1!
1*
b111 /
#12499800
0!
0*
#12541466
1!
1*
b1000 /
#12583132
0!
0*
#12624798
1!
1*
b1001 /
#12666464
0!
0*
#12708130
1!
1*
b1010 /
1-
b0 /
1%
#12749796
0!
0*
#12791462
1!
1*
b1 /
0-
0%
#12833128
0!
0*
#12874794
1!
1*
b10 /
#12916460
0!
0*
#12958126
1!
1*
b11 /
#12999792
0!
0*
#13041458
1!
1*
b100 /
#13083124
0!
0*
#13124790
1!
1*
b101 /
#13166456
0!
0*
#13208122
1!
1*
b110 /
#13249788
0!
0*
#13291454
1!
1*
b111 /
#13333120
0!
0*
#13374786
1!
1*
b1000 /
#13416452
0!
0*
#13458118
1!
1*
b1001 /
#13499784
0!
0*
#13541450
1!
1*
b1010 /
1-
b0 /
1%
#13583116
0!
0*
#13624782
1!
1*
b1 /
0-
0%
#13666448
0!
0*
#13708114
1!
1*
b10 /
#13749780
0!
0*
#13791446
1!
1*
b11 /
#13833112
0!
0*
#13874778
1!
1*
b100 /
#13916444
0!
0*
#13958110
1!
1*
b101 /
#13999776
0!
0*
#14041442
1!
1*
b110 /
#14083108
0!
0*
#14124774
1!
1*
b111 /
#14166440
0!
0*
#14208106
1!
1*
b1000 /
#14249772
0!
0*
#14291438
1!
1*
b1001 /
#14333104
0!
0*
#14374770
1!
1*
b1010 /
1-
b0 /
1%
#14416436
0!
0*
#14458102
1!
1*
b1 /
0-
0%
#14499768
0!
0*
#14541434
1!
1*
b10 /
#14583100
0!
0*
#14624766
1!
1*
b11 /
#14666432
0!
0*
#14708098
1!
1*
b100 /
#14749764
0!
0*
#14791430
1!
1*
b101 /
#14833096
0!
0*
#14874762
1!
1*
b110 /
#14916428
0!
0*
#14958094
1!
1*
b111 /
#14999760
0!
0*
#15041426
1!
1*
b1000 /
#15083092
0!
0*
#15124758
1!
1*
b1001 /
#15166424
0!
0*
#15208090
1!
1*
b1010 /
1-
b0 /
1%
#15249756
0!
0*
#15291422
1!
1*
b1 /
0-
0%
#15333088
0!
0*
#15374754
1!
1*
b10 /
#15416420
0!
0*
#15458086
1!
1*
b11 /
#15499752
0!
0*
#15541418
1!
1*
b100 /
#15583084
0!
0*
#15624750
1!
1*
b101 /
#15666416
0!
0*
#15708082
1!
1*
b110 /
#15749748
0!
0*
#15791414
1!
1*
b111 /
#15833080
0!
0*
#15874746
1!
1*
b1000 /
#15916412
0!
0*
#15958078
1!
1*
b1001 /
#15999744
0!
0*
#16041410
1!
1*
b1010 /
1-
b0 /
1%
#16083076
0!
0*
#16124742
1!
1*
b1 /
0-
0%
#16166408
0!
0*
#16208074
1!
1*
b10 /
#16249740
0!
0*
#16291406
1!
1*
b11 /
#16333072
0!
0*
#16374738
1!
1*
b100 /
#16416404
0!
0*
#16458070
1!
1*
b101 /
#16499736
0!
0*
#16541402
1!
1*
b110 /
#16583068
0!
0*
#16624734
1!
1*
b111 /
#16666400
0!
0*
#16708066
1!
1*
b1000 /
#16749732
0!
0*
#16791398
1!
1*
b1001 /
#16833064
0!
0*
#16874730
1!
1*
b1010 /
1-
b0 /
1%
#16916396
0!
0*
#16958062
1!
1*
b1 /
0-
0%
#16999728
0!
0*
#17041394
1!
1*
b10 /
#17083060
0!
0*
#17124726
1!
1*
b11 /
#17166392
0!
0*
#17208058
1!
1*
b100 /
#17249724
0!
0*
#17291390
1!
1*
b101 /
#17333056
0!
0*
#17374722
1!
1*
b110 /
#17416388
0!
0*
#17458054
1!
1*
b111 /
#17499720
0!
0*
#17541386
1!
1*
b1000 /
#17583052
0!
0*
#17624718
1!
1*
b1001 /
#17666384
0!
0*
#17708050
1!
1*
b1010 /
1-
b0 /
1%
#17749716
0!
0*
#17791382
1!
1*
b1 /
0-
0%
#17833048
0!
0*
#17874714
1!
1*
b10 /
#17916380
0!
0*
#17958046
1!
1*
b11 /
#17999712
0!
0*
#18041378
1!
1*
b100 /
#18083044
0!
0*
#18124710
1!
1*
b101 /
#18166376
0!
0*
#18208042
1!
1*
b110 /
#18249708
0!
0*
#18291374
1!
1*
b111 /
#18333040
0!
0*
#18374706
1!
1*
b1000 /
#18416372
0!
0*
#18458038
1!
1*
b1001 /
#18499704
0!
0*
#18541370
1!
1*
b1010 /
1-
b0 /
1%
#18583036
0!
0*
#18624702
1!
1*
b1 /
0-
0%
#18666368
0!
0*
#18708034
1!
1*
b10 /
#18749700
0!
0*
#18791366
1!
1*
b11 /
#18833032
0!
0*
#18874698
1!
1*
b100 /
#18916364
0!
0*
#18958030
1!
1*
b101 /
#18999696
0!
0*
#19041362
1!
1*
b110 /
#19083028
0!
0*
#19124694
1!
1*
b111 /
#19166360
0!
0*
#19208026
1!
1*
b1000 /
#19249692
0!
0*
#19291358
1!
1*
b1001 /
#19333024
0!
0*
#19374690
1!
1*
b1010 /
1-
b0 /
1%
#19416356
0!
0*
#19458022
1!
1*
b1 /
0-
0%
#19499688
0!
0*
#19541354
1!
1*
b10 /
#19583020
0!
0*
#19624686
1!
1*
b11 /
#19666352
0!
0*
#19708018
1!
1*
b100 /
#19749684
0!
0*
#19791350
1!
1*
b101 /
#19833016
0!
0*
#19874682
1!
1*
b110 /
#19916348
0!
0*
#19958014
1!
1*
b111 /
#19999680
0!
0*
#20041346
1!
1*
b1000 /
#20083012
0!
0*
#20124678
1!
1*
b1001 /
#20166344
0!
0*
#20208010
1!
1*
b1010 /
1-
b0 /
1%
#20249676
0!
0*
#20291342
1!
1*
b1 /
0-
0%
#20333008
0!
0*
#20374674
1!
1*
b10 /
#20416340
0!
0*
#20458006
1!
1*
b11 /
#20499672
0!
0*
#20541338
1!
1*
b100 /
#20583004
0!
0*
#20624670
1!
1*
b101 /
#20666336
0!
0*
#20708002
1!
1*
b110 /
#20749668
0!
0*
#20791334
1!
1*
b111 /
#20833000
0!
0*
#20874666
1!
1*
b1000 /
#20916332
0!
0*
#20957998
1!
1*
b1001 /
#20999664
0!
0*
#21041330
1!
1*
b1010 /
1-
b0 /
1%
#21082996
0!
0*
#21124662
1!
1*
b1 /
0-
0%
#21166328
0!
0*
#21207994
1!
1*
b10 /
#21249660
0!
0*
#21291326
1!
1*
b11 /
#21332992
0!
0*
#21374658
1!
1*
b100 /
#21416324
0!
0*
#21457990
1!
1*
b101 /
#21499656
0!
0*
#21541322
1!
1*
b110 /
#21582988
0!
0*
#21624654
1!
1*
b111 /
#21666320
0!
0*
#21707986
1!
1*
b1000 /
#21749652
0!
0*
#21791318
1!
1*
b1001 /
#21832984
0!
0*
#21874650
1!
1*
b1010 /
1-
b0 /
1%
#21916316
0!
0*
#21957982
1!
1*
b1 /
0-
0%
#21999648
0!
0*
#22041314
1!
1*
b10 /
#22082980
0!
0*
#22124646
1!
1*
b11 /
#22166312
0!
0*
#22207978
1!
1*
b100 /
#22249644
0!
0*
#22291310
1!
1*
b101 /
#22332976
0!
0*
#22374642
1!
1*
b110 /
#22416308
0!
0*
#22457974
1!
1*
b111 /
#22499640
0!
0*
#22541306
1!
1*
b1000 /
#22582972
0!
0*
#22624638
1!
1*
b1001 /
#22666304
0!
0*
#22707970
1!
1*
b1010 /
1-
b0 /
1%
#22749636
0!
0*
#22791302
1!
1*
b1 /
0-
0%
#22832968
0!
0*
#22874634
1!
1*
b10 /
#22916300
0!
0*
#22957966
1!
1*
b11 /
#22999632
0!
0*
#23041298
1!
1*
b100 /
#23082964
0!
0*
#23124630
1!
1*
b101 /
#23166296
0!
0*
#23207962
1!
1*
b110 /
#23249628
0!
0*
#23291294
1!
1*
b111 /
#23332960
0!
0*
#23374626
1!
1*
b1000 /
#23416292
0!
0*
#23457958
1!
1*
b1001 /
#23499624
0!
0*
#23541290
1!
1*
b1010 /
1-
b0 /
1%
#23582956
0!
0*
#23624622
1!
1*
b1 /
0-
0%
#23666288
0!
0*
#23707954
1!
1*
b10 /
#23749620
0!
0*
#23791286
1!
1*
b11 /
#23832952
0!
0*
#23874618
1!
1*
b100 /
#23916284
0!
0*
#23957950
1!
1*
b101 /
#23999616
0!
0*
#24041282
1!
1*
b110 /
#24082948
0!
0*
#24124614
1!
1*
b111 /
#24166280
0!
0*
#24207946
1!
1*
b1000 /
#24249612
0!
0*
#24291278
1!
1*
b1001 /
#24332944
0!
0*
#24374610
1!
1*
b1010 /
1-
b0 /
1%
#24416276
0!
0*
#24457942
1!
1*
b1 /
0-
0%
#24499608
0!
0*
#24541274
1!
1*
b10 /
#24582940
0!
0*
#24624606
1!
1*
b11 /
#24666272
0!
0*
#24707938
1!
1*
b100 /
#24749604
0!
0*
#24791270
1!
1*
b101 /
#24832936
0!
0*
#24874602
1!
1*
b110 /
#24916268
0!
0*
#24957934
1!
1*
b111 /
#24999600
0!
0*
#25041266
1!
1*
b1000 /
#25082932
0!
0*
#25124598
1!
1*
b1001 /
#25166264
0!
0*
#25207930
1!
1*
b1010 /
1-
b0 /
1%
#25249596
0!
0*
#25291262
1!
1*
b1 /
0-
0%
#25332928
0!
0*
#25374594
1!
1*
b10 /
#25416260
0!
0*
#25457926
1!
1*
b11 /
#25499592
0!
0*
#25541258
1!
1*
b100 /
#25582924
0!
0*
#25624590
1!
1*
b101 /
#25666256
0!
0*
#25707922
1!
1*
b110 /
#25749588
0!
0*
#25791254
1!
1*
b111 /
#25832920
0!
0*
#25874586
1!
1*
b1000 /
#25916252
0!
0*
#25957918
1!
1*
b1001 /
#25999584
0!
0*
#26041250
1!
1*
b1010 /
1-
b0 /
1%
#26082916
0!
0*
#26124582
1!
1*
b1 /
0-
0%
#26166248
0!
0*
#26207914
1!
1*
b10 /
#26249580
0!
0*
#26291246
1!
1*
b11 /
#26332912
0!
0*
#26374578
1!
1*
b100 /
#26416244
0!
0*
#26457910
1!
1*
b101 /
#26499576
0!
0*
#26541242
1!
1*
b110 /
#26582908
0!
0*
#26624574
1!
1*
b111 /
#26666240
0!
0*
#26707906
1!
1*
b1000 /
#26749572
0!
0*
#26791238
1!
1*
b1001 /
#26832904
0!
0*
#26874570
1!
1*
b1010 /
1-
b0 /
1%
#26916236
0!
0*
#26957902
1!
1*
b1 /
0-
0%
#26999568
0!
0*
#27041234
1!
1*
b10 /
#27082900
0!
0*
#27124566
1!
1*
b11 /
#27166232
0!
0*
#27207898
1!
1*
b100 /
#27249564
0!
0*
#27291230
1!
1*
b101 /
#27332896
0!
0*
#27374562
1!
1*
b110 /
#27416228
0!
0*
#27457894
1!
1*
b111 /
#27499560
0!
0*
#27541226
1!
1*
b1000 /
#27582892
0!
0*
#27624558
1!
1*
b1001 /
#27666224
0!
0*
#27707890
1!
1*
b1010 /
1-
b0 /
1%
#27749556
0!
0*
#27791222
1!
1*
b1 /
0-
0%
#27832888
0!
0*
#27874554
1!
1*
b10 /
#27916220
0!
0*
#27957886
1!
1*
b11 /
#27999552
0!
0*
#28041218
1!
1*
b100 /
#28082884
0!
0*
#28124550
1!
1*
b101 /
#28166216
0!
0*
#28207882
1!
1*
b110 /
#28249548
0!
0*
#28291214
1!
1*
b111 /
#28332880
0!
0*
#28374546
1!
1*
b1000 /
#28416212
0!
0*
#28457878
1!
1*
b1001 /
#28499544
0!
0*
#28541210
1!
1*
b1010 /
1-
b0 /
1%
#28582876
0!
0*
#28624542
1!
1*
b1 /
0-
0%
#28666208
0!
0*
#28707874
1!
1*
b10 /
#28749540
0!
0*
#28791206
1!
1*
b11 /
#28832872
0!
0*
#28874538
1!
1*
b100 /
#28916204
0!
0*
#28957870
1!
1*
b101 /
#28999536
0!
0*
#29041202
1!
1*
b110 /
#29082868
0!
0*
#29124534
1!
1*
b111 /
#29166200
0!
0*
#29207866
1!
1*
b1000 /
#29249532
0!
0*
#29291198
1!
1*
b1001 /
#29332864
0!
0*
#29374530
1!
1*
b1010 /
1-
b0 /
1%
#29416196
0!
0*
#29457862
1!
1*
b1 /
0-
0%
#29499528
0!
0*
#29541194
1!
1*
b10 /
#29582860
0!
0*
#29624526
1!
1*
b11 /
#29666192
0!
0*
#29707858
1!
1*
b100 /
#29749524
0!
0*
#29791190
1!
1*
b101 /
#29832856
0!
0*
#29874522
1!
1*
b110 /
#29916188
0!
0*
#29957854
1!
1*
b111 /
#29999520
0!
0*
#30041186
1!
1*
b1000 /
#30082852
0!
0*
#30124518
1!
1*
b1001 /
#30166184
0!
0*
#30207850
1!
1*
b1010 /
1-
b0 /
1%
#30249516
0!
0*
#30291182
1!
1*
b1 /
0-
0%
#30332848
0!
0*
#30374514
1!
1*
b10 /
#30416180
0!
0*
#30457846
1!
1*
b11 /
#30499512
0!
0*
#30541178
1!
1*
b100 /
#30582844
0!
0*
#30624510
1!
1*
b101 /
#30666176
0!
0*
#30707842
1!
1*
b110 /
#30749508
0!
0*
#30791174
1!
1*
b111 /
#30832840
0!
0*
#30874506
1!
1*
b1000 /
#30916172
0!
0*
#30957838
1!
1*
b1001 /
#30999504
0!
0*
#31041170
1!
1*
b1010 /
1-
b0 /
1%
#31082836
0!
0*
#31124502
1!
1*
b1 /
0-
0%
#31166168
0!
0*
#31207834
1!
1*
b10 /
#31249500
0!
0*
#31291166
1!
1*
b11 /
#31332832
0!
0*
#31374498
1!
1*
b100 /
#31416164
0!
0*
#31457830
1!
1*
b101 /
#31499496
0!
0*
#31541162
1!
1*
b110 /
#31582828
0!
0*
#31624494
1!
1*
b111 /
#31666160
0!
0*
#31707826
1!
1*
b1000 /
#31749492
0!
0*
#31791158
1!
1*
b1001 /
#31832824
0!
0*
#31874490
1!
1*
b1010 /
1-
b0 /
1%
#31916156
0!
0*
#31957822
1!
1*
b1 /
0-
0%
#31999488
0!
0*
#32041154
1!
1*
b10 /
#32082820
0!
0*
#32124486
1!
1*
b11 /
#32166152
0!
0*
#32207818
1!
1*
b100 /
#32249484
0!
0*
#32291150
1!
1*
b101 /
#32332816
0!
0*
#32374482
1!
1*
b110 /
#32416148
0!
0*
#32457814
1!
1*
b111 /
#32499480
0!
0*
#32541146
1!
1*
b1000 /
#32582812
0!
0*
#32624478
1!
1*
b1001 /
#32666144
0!
0*
#32707810
1!
1*
b1010 /
1-
b0 /
1%
#32749476
0!
0*
